{
    "labelAnnotations": [
        {
            "mid": "/m/08863x",
            "description": "bird's eye view",
            "score": 0.87366915,
            "topicality": 0.87366915
        },
        {
            "mid": "/m/039jbq",
            "description": "urban area",
            "score": 0.83781034,
            "topicality": 0.83781034
        },
        {
            "mid": "/m/01w5c_",
            "description": "aerial photography",
            "score": 0.81499296,
            "topicality": 0.81499296
        },
        {
            "mid": "/m/01n32",
            "description": "city",
            "score": 0.7471021,
            "topicality": 0.7471021
        },
        {
            "mid": "/m/02nfxt",
            "description": "residential area",
            "score": 0.73238546,
            "topicality": 0.73238546
        },
        {
            "mid": "/m/0180xr",
            "description": "neighbourhood",
            "score": 0.7285206,
            "topicality": 0.7285206
        },
        {
            "mid": "/m/0750y",
            "description": "suburb",
            "score": 0.6868994,
            "topicality": 0.6868994
        },
        {
            "mid": "/m/0d9wj",
            "description": "urban design",
            "score": 0.6433076,
            "topicality": 0.6433076
        },
        {
            "mid": "/m/023907r",
            "description": "real estate",
            "score": 0.6169789,
            "topicality": 0.6169789
        },
        {
            "mid": "/m/0gs32y",
            "description": "land lot",
            "score": 0.5704816,
            "topicality": 0.5704816
        },
        {
            "mid": "/m/025s3q0",
            "description": "landscape",
            "score": 0.5022189,
            "topicality": 0.5022189
        }
    ],
    "safeSearchAnnotation": {
        "adult": "VERY_UNLIKELY",
        "spoof": "VERY_UNLIKELY",
        "medical": "VERY_UNLIKELY",
        "violence": "VERY_UNLIKELY",
        "racy": "VERY_UNLIKELY"
    },
    "imagePropertiesAnnotation": {
        "dominantColors": {
            "colors": [
                {
                    "color": {
                        "red": 174,
                        "green": 155,
                        "blue": 130
                    },
                    "score": 0.17383714,
                    "pixelFraction": 0.1397079
                },
                {
                    "color": {
                        "red": 209,
                        "green": 188,
                        "blue": 164
                    },
                    "score": 0.11596193,
                    "pixelFraction": 0.03999454
                },
                {
                    "color": {
                        "red": 194,
                        "green": 143,
                        "blue": 121
                    },
                    "score": 0.1154528,
                    "pixelFraction": 0.017199017
                },
                {
                    "color": {
                        "red": 210,
                        "green": 144,
                        "blue": 100
                    },
                    "score": 0.07301967,
                    "pixelFraction": 0.0052552554
                },
                {
                    "color": {
                        "red": 136,
                        "green": 118,
                        "blue": 91
                    },
                    "score": 0.05815152,
                    "pixelFraction": 0.088452086
                },
                {
                    "color": {
                        "red": 222,
                        "green": 178,
                        "blue": 158
                    },
                    "score": 0.04406863,
                    "pixelFraction": 0.006688507
                },
                {
                    "color": {
                        "red": 155,
                        "green": 115,
                        "blue": 95
                    },
                    "score": 0.034804847,
                    "pixelFraction": 0.011670762
                },
                {
                    "color": {
                        "red": 212,
                        "green": 195,
                        "blue": 186
                    },
                    "score": 0.030178614,
                    "pixelFraction": 0.01030576
                },
                {
                    "color": {
                        "red": 173,
                        "green": 158,
                        "blue": 101
                    },
                    "score": 0.028790988,
                    "pixelFraction": 0.03050778
                },
                {
                    "color": {
                        "red": 129,
                        "green": 120,
                        "blue": 65
                    },
                    "score": 0.025755173,
                    "pixelFraction": 0.053439803
                }
            ]
        }
    },
    "cropHintsAnnotation": {
        "cropHints": [
            {
                "boundingPoly": {
                    "vertices": [
                        [],
                        {
                            "x": 959
                        },
                        {
                            "x": 959,
                            "y": 639
                        },
                        {
                            "y": 639
                        }
                    ]
                },
                "confidence": 0.79999995,
                "importanceFraction": 1
            }
        ]
    },
    "webDetection": {
        "webEntities": [
            {
                "entityId": "/g/11bvt4sxv0",
                "score": 0.93258,
                "description": "2016 Warsaw summit"
            },
            {
                "entityId": "/g/11b5t_qyd0",
                "score": 0.91065,
                "description": "NATO Headquarters"
            },
            {
                "entityId": "/g/1hc5wr3b5",
                "score": 0.80696005,
                "description": "NATO Communications and Information Agency"
            },
            {
                "entityId": "/m/0k0vt90",
                "score": 0.727,
                "description": "NATO Communications and Information Agency"
            },
            {
                "entityId": "/t/27cdxz_3bh16y",
                "score": 0.7214
            },
            {
                "entityId": "/m/059dn",
                "score": 0.7214,
                "description": "NATO"
            },
            {
                "entityId": "/m/04zycj8",
                "score": 0.5785,
                "description": "iGeoSIT"
            },
            {
                "entityId": "/m/0fm88",
                "score": 0.52155,
                "description": "Mons"
            },
            {
                "entityId": "/m/0403mhs",
                "score": 0.5194,
                "description": "NATO Communications and Information Systems Services Agency"
            },
            {
                "entityId": "/g/11fytq281m",
                "score": 0.5159
            },
            {
                "entityId": "/m/04zznvt",
                "score": 0.4762,
                "description": "Alliance Ground Surveillance"
            },
            {
                "entityId": "/t/23p50h_kgbnhm",
                "score": 0.4014
            },
            {
                "entityId": "/m/09rwgqq",
                "score": 0.3795,
                "description": "NATO Rapid Deployable Corps \u2013 Italy"
            },
            {
                "entityId": "/m/07g0_",
                "score": 0.21591,
                "description": "The Hague"
            },
            {
                "entityId": "/m/02r330x",
                "score": 0.12345,
                "description": "NATO summit"
            }
        ],
        "fullMatchingImages": [
            {
                "url": "https://upload.wikimedia.org/wikipedia/commons/d/d4/NATO_complex_The_Hague%2C_Waalsdorperweg.jpg"
            },
            {
                "url": "http://i.imgur.com/qO3AaqX.jpg"
            },
            {
                "url": "https://upload.wikimedia.org/wikipedia/commons/thumb/d/d4/NATO_complex_The_Hague%2C_Waalsdorperweg.jpg/640px-NATO_complex_The_Hague%2C_Waalsdorperweg.jpg"
            },
            {
                "url": "https://www.alterinfo.net/photo/art/default/22535137-25193413.jpg?v=1527444712"
            },
            {
                "url": "https://upload.wikimedia.org/wikipedia/commons/thumb/d/d4/NATO_complex_The_Hague%2C_Waalsdorperweg.jpg/320px-NATO_complex_The_Hague%2C_Waalsdorperweg.jpg"
            },
            {
                "url": "https://www.fueakbw.de/images/thumbnails/images/Artikel/Europa_LGAN_2017_03_20/Foto_8-fill-300x208.jpg"
            },
            {
                "url": "https://upload.wikimedia.org/wikipedia/commons/thumb/d/d4/NATO_complex_The_Hague%2C_Waalsdorperweg.jpg/266px-NATO_complex_The_Hague%2C_Waalsdorperweg.jpg"
            },
            {
                "url": "https://upload.wikimedia.org/wikipedia/commons/thumb/d/d4/NATO_complex_The_Hague%2C_Waalsdorperweg.jpg/250px-NATO_complex_The_Hague%2C_Waalsdorperweg.jpg"
            },
            {
                "url": "https://upload.wikimedia.org/wikipedia/commons/thumb/d/d4/NATO_complex_The_Hague%2C_Waalsdorperweg.jpg/220px-NATO_complex_The_Hague%2C_Waalsdorperweg.jpg"
            },
            {
                "url": "https://www.avecodebondt.nl/dynamics/modules/SFIL0200/view.php?fil_Id=6533&thumb_nr=4"
            },
            {
                "url": "https://upload.wikimedia.org/wikipedia/commons/thumb/d/d4/NATO_complex_The_Hague%2C_Waalsdorperweg.jpg/200px-NATO_complex_The_Hague%2C_Waalsdorperweg.jpg"
            }
        ],
        "partialMatchingImages": [
            {
                "url": "http://www.defenseworld.net/uploads//news/big/nci_agenc_1469711131.jpg"
            }
        ],
        "pagesWithMatchingImages": [
            {
                "url": "https://en.wikipedia.org/wiki/NATO_Communications_and_Information_Agency",
                "pageTitle": "<b>NATO</b> Communications and Information Agency - Wikipedia",
                "fullMatchingImages": [
                    {
                        "url": "https://upload.wikimedia.org/wikipedia/commons/thumb/d/d4/NATO_complex_The_Hague%2C_Waalsdorperweg.jpg/220px-NATO_complex_The_Hague%2C_Waalsdorperweg.jpg"
                    }
                ]
            },
            {
                "url": "https://commons.wikimedia.org/wiki/File:NATO_complex_The_Hague,_Waalsdorperweg.jpg",
                "pageTitle": "File:<b>NATO</b> complex <b>The Hague</b>, Waalsdorperweg.jpg - Wikimedia ...",
                "fullMatchingImages": [
                    {
                        "url": "https://upload.wikimedia.org/wikipedia/commons/thumb/d/d4/NATO_complex_The_Hague%2C_Waalsdorperweg.jpg/320px-NATO_complex_The_Hague%2C_Waalsdorperweg.jpg"
                    },
                    {
                        "url": "https://upload.wikimedia.org/wikipedia/commons/d/d4/NATO_complex_The_Hague%2C_Waalsdorperweg.jpg"
                    },
                    {
                        "url": "https://upload.wikimedia.org/wikipedia/commons/thumb/d/d4/NATO_complex_The_Hague%2C_Waalsdorperweg.jpg/640px-NATO_complex_The_Hague%2C_Waalsdorperweg.jpg"
                    }
                ]
            },
            {
                "url": "https://www.picswe.com/pics/nato-ncia-2f.html",
                "pageTitle": "<b>Nato</b> Ncia | www.picswe.com",
                "fullMatchingImages": [
                    {
                        "url": "https://www.rijksvastgoedbedrijf.nl/binaries/large/content/gallery/rijksvastgoedbedrijf/content-afbeeldingen/vastgoed/den-haag-nato-ncia/nato-complex-waalsdorperweg-61-den-haag.jpg"
                    }
                ]
            },
            {
                "url": "http://parallel-welten.info/live/suggestions/ncia-nato/",
                "pageTitle": "Ncia <b>Nato</b> - parallel-welten.info",
                "fullMatchingImages": [
                    {
                        "url": "https://www.rijksvastgoedbedrijf.nl/binaries/large/content/gallery/rijksvastgoedbedrijf/content-afbeeldingen/vastgoed/den-haag-nato-ncia/nato-complex-waalsdorperweg-61-den-haag.jpg"
                    }
                ]
            },
            {
                "url": "https://www.wikidata.org/wiki/Q6953132",
                "pageTitle": "NCIA - Wikidata",
                "fullMatchingImages": [
                    {
                        "url": "https://upload.wikimedia.org/wikipedia/commons/d/d4/NATO_complex_The_Hague%2C_Waalsdorperweg.jpg"
                    }
                ]
            },
            {
                "url": "http://cerev.info/addzthis-ncia,-the-hague.htm",
                "pageTitle": "Ncia, <b>The Hague</b> - More info",
                "fullMatchingImages": [
                    {
                        "url": "https://www.rijksvastgoedbedrijf.nl/binaries/large/content/gallery/rijksvastgoedbedrijf/content-afbeeldingen/vastgoed/den-haag-nato-ncia/nato-complex-waalsdorperweg-61-den-haag.jpg"
                    }
                ]
            },
            {
                "url": "http://www.defenseworld.net/news/17960/NATO_Uses_Italtel___s_Transportable_Data_Centers_For____Summer_Tempest___Eagle_Meteor_2016____Training_Exercise",
                "pageTitle": "<b>NATO</b> Uses Italtel&#39;s Transportable Data Centers For \u201cSummer ...",
                "partialMatchingImages": [
                    {
                        "url": "http://www.defenseworld.net/uploads//news/big/nci_agenc_1469711131.jpg"
                    }
                ]
            },
            {
                "url": "http://www.defenseworld.net/news/16540/Leonardo_Finmeccancia_To_Present_NATO_Alliance_Ground_Surveillance_System_During_Warsaw_Summit",
                "pageTitle": "Leonardo-Finmeccancia To Present <b>NATO</b> Alliance Ground ...",
                "partialMatchingImages": [
                    {
                        "url": "http://www.defenseworld.net/uploads//news/big/nci_agenc_1469711131.jpg"
                    }
                ]
            },
            {
                "url": "http://www.defenseworld.net/news/16339/Weaponized_Version_of_Polish_Black_Hawk_Helicopter_To_Debut_At_NATO_Exercise",
                "pageTitle": "Weaponized Version of Polish Black Hawk Helicopter To Debut At ...",
                "partialMatchingImages": [
                    {
                        "url": "http://www.defenseworld.net/uploads//news/big/nci_agenc_1469711131.jpg"
                    }
                ]
            },
            {
                "url": "http://www.defenseworld.net/news/16676/Fire_Erupts_Near_NATO_Base_In_Turkey__Sabotage_Suspected",
                "pageTitle": "Fire Erupts Near <b>NATO</b> Base In Turkey, Sabotage Suspected",
                "partialMatchingImages": [
                    {
                        "url": "http://www.defenseworld.net/uploads//news/big/nci_agenc_1469711131.jpg"
                    }
                ]
            },
            {
                "url": "https://wikivisually.com/wiki/NATO_Communications_and_Information_Systems_Services_Agency",
                "pageTitle": "<b>NATO</b> Communications and Information Systems Services Agency ...",
                "fullMatchingImages": [
                    {
                        "url": "https://upload.wikimedia.org/wikipedia/commons/thumb/d/d4/NATO_complex_The_Hague%2C_Waalsdorperweg.jpg/250px-NATO_complex_The_Hague%2C_Waalsdorperweg.jpg"
                    }
                ]
            },
            {
                "url": "http://zakopianskie.info/ncia-nato/",
                "pageTitle": "Ncia <b>Nato</b> - Zakopianskie",
                "fullMatchingImages": [
                    {
                        "url": "https://www.rijksvastgoedbedrijf.nl/binaries/large/content/gallery/rijksvastgoedbedrijf/content-afbeeldingen/vastgoed/den-haag-nato-ncia/nato-complex-waalsdorperweg-61-den-haag.jpg"
                    }
                ]
            },
            {
                "url": "https://wikivisually.com/wiki/iGeoSIT",
                "pageTitle": "iGeoSIT - WikiVisually",
                "fullMatchingImages": [
                    {
                        "url": "https://upload.wikimedia.org/wikipedia/commons/thumb/d/d4/NATO_complex_The_Hague%2C_Waalsdorperweg.jpg/250px-NATO_complex_The_Hague%2C_Waalsdorperweg.jpg"
                    }
                ]
            },
            {
                "url": "https://www.rijksvastgoedbedrijf.nl/vastgoed/projecten-in-uitvoering/den-haag-nato-complex",
                "pageTitle": "<b>Den Haag</b>, <b>NATO</b>-complex | Vastgoed | Rijksvastgoedbedrijf",
                "fullMatchingImages": [
                    {
                        "url": "https://www.rijksvastgoedbedrijf.nl/binaries/large/content/gallery/rijksvastgoedbedrijf/content-afbeeldingen/vastgoed/den-haag-nato-ncia/nato-complex-waalsdorperweg-61-den-haag.jpg"
                    }
                ]
            },
            {
                "url": "https://nl.wikipedia.org/wiki/NATO_Communications_and_Information_Agency",
                "pageTitle": "<b>NATO</b> Communications and Information Agency - Wikipedia",
                "fullMatchingImages": [
                    {
                        "url": "https://upload.wikimedia.org/wikipedia/commons/thumb/d/d4/NATO_complex_The_Hague%2C_Waalsdorperweg.jpg/266px-NATO_complex_The_Hague%2C_Waalsdorperweg.jpg"
                    }
                ]
            },
            {
                "url": "https://de.wikipedia.org/wiki/NATO_Communications_and_Information_Agency",
                "pageTitle": "<b>NATO</b> Communications and Information Agency \u2013 Wikipedia",
                "fullMatchingImages": [
                    {
                        "url": "https://upload.wikimedia.org/wikipedia/commons/thumb/d/d4/NATO_complex_The_Hague%2C_Waalsdorperweg.jpg/220px-NATO_complex_The_Hague%2C_Waalsdorperweg.jpg"
                    }
                ]
            },
            {
                "url": "https://nl.wikipedia.org/wiki/Bestand:NATO_complex_The_Hague,_Waalsdorperweg.jpg",
                "pageTitle": "Bestand:<b>NATO</b> complex <b>The Hague</b>, Waalsdorperweg.jpg - Wikipedia",
                "fullMatchingImages": [
                    {
                        "url": "https://upload.wikimedia.org/wikipedia/commons/thumb/d/d4/NATO_complex_The_Hague%2C_Waalsdorperweg.jpg/320px-NATO_complex_The_Hague%2C_Waalsdorperweg.jpg"
                    },
                    {
                        "url": "https://upload.wikimedia.org/wikipedia/commons/d/d4/NATO_complex_The_Hague%2C_Waalsdorperweg.jpg"
                    },
                    {
                        "url": "https://upload.wikimedia.org/wikipedia/commons/thumb/d/d4/NATO_complex_The_Hague%2C_Waalsdorperweg.jpg/640px-NATO_complex_The_Hague%2C_Waalsdorperweg.jpg"
                    }
                ]
            },
            {
                "url": "https://www.avecodebondt.nl/nl/projecten/detail/ncia",
                "pageTitle": "NCIA - Aveco de Bondt",
                "fullMatchingImages": [
                    {
                        "url": "https://www.avecodebondt.nl/dynamics/modules/SFIL0200/view.php?fil_Id=6533&thumb_nr=4"
                    }
                ]
            },
            {
                "url": "https://www.skyscrapercity.com/showthread.php?t=411651&page=59",
                "pageTitle": "<b>Den Haag</b>: Projectenoverzicht - Page 59 - SkyscraperCity",
                "fullMatchingImages": [
                    {
                        "url": "http://i.imgur.com/qO3AaqX.jpg"
                    }
                ]
            },
            {
                "url": "https://www.fueakbw.de/index.php/de/aktuelles/170-europareise-fuer-angehoerige-der-fuehrungsakademie",
                "pageTitle": "Europareise f\u00fcr Angeh\u00f6rige der F\u00fchrungsakademie",
                "fullMatchingImages": [
                    {
                        "url": "https://www.fueakbw.de/images/Artikel/Europa_LGAN_2017_03_20/Foto_8.jpg"
                    }
                ]
            },
            {
                "url": "https://www.skyscrapercity.com/showthread.php?p=128338526",
                "pageTitle": "<b>Den Haag</b>: Projectenoverzicht - Page 59 - SkyscraperCity",
                "fullMatchingImages": [
                    {
                        "url": "http://i.imgur.com/qO3AaqX.jpg"
                    }
                ]
            },
            {
                "url": "https://www.skyscrapercity.com/showthread.php?t=411651&page=66",
                "pageTitle": "<b>Den Haag</b>: Projectenoverzicht - Page 66 - SkyscraperCity",
                "fullMatchingImages": [
                    {
                        "url": "https://upload.wikimedia.org/wikipedia/commons/d/d4/NATO_complex_The_Hague%2C_Waalsdorperweg.jpg"
                    }
                ]
            },
            {
                "url": "https://www.fueakbw.de/index.php/de/aktuelles?start=195",
                "pageTitle": "Aktuelles - F\u00fchrungsakademie der Bundeswehr",
                "fullMatchingImages": [
                    {
                        "url": "https://www.fueakbw.de/images/thumbnails/images/Artikel/Europa_LGAN_2017_03_20/Foto_8-fill-300x208.jpg"
                    }
                ]
            },
            {
                "url": "http://dede14.com/den-medie-die-nato-und-den",
                "pageTitle": "<b>Den</b> Medie Die <b>Nato</b> Und <b>Den</b> \u2013 dede14",
                "fullMatchingImages": [
                    {
                        "url": "https://upload.wikimedia.org/wikipedia/commons/d/d4/NATO_complex_The_Hague%2C_Waalsdorperweg.jpg"
                    }
                ]
            },
            {
                "url": "https://stopmensonges.com/category/categories/physique-quantique-technologie/page/3/",
                "pageTitle": "Physique Quantique &amp; Technologie | Stop Mensonges | Page 3",
                "fullMatchingImages": [
                    {
                        "url": "http://www.alterinfo.net/photo/art/default/22535137-25193413.jpg?v=1527444712"
                    }
                ]
            },
            {
                "url": "http://www.alterinfo.net/notes/Otan-un-rapport-propose-un-article-5-bis-contre-la-guerre-hybride_b22535137.html",
                "pageTitle": "Otan: un rapport propose un \u00ab article 5 bis \u00bb contre la guerre ...",
                "fullMatchingImages": [
                    {
                        "url": "http://www.alterinfo.net/photo/art/default/22535137-25193413.jpg?v=1527444712"
                    }
                ]
            },
            {
                "url": "https://stopmensonges.com/2017/10/page/2/",
                "pageTitle": "octobre | 2017 | Stop Mensonges | Page 2",
                "fullMatchingImages": [
                    {
                        "url": "http://www.alterinfo.net/photo/art/default/22535137-25193413.jpg?v=1527444712"
                    }
                ]
            },
            {
                "url": "https://stopmensonges.com/etats-unis-lenquete-sur-les-e-mails-dhillary-clinton-rouverte/",
                "pageTitle": "\u00c9tats-Unis : l&#39;enqu\u00eate sur les e-mails d&#39;Hillary Clinton rouverte ...",
                "fullMatchingImages": [
                    {
                        "url": "http://www.alterinfo.net/photo/art/default/22535137-25193413.jpg?v=1527444712"
                    }
                ]
            },
            {
                "url": "https://stopmensonges.com/tag/disclosure-project/",
                "pageTitle": "disclosure project | Stop Mensonges",
                "fullMatchingImages": [
                    {
                        "url": "http://www.alterinfo.net/photo/art/default/22535137-25193413.jpg?v=1527444712"
                    }
                ]
            },
            {
                "url": "https://m.epochtimes.fr/otan-un-rapport-propose-un-article-5-bis-contre-la-guerre-hybride-330369.html",
                "pageTitle": "Otan: un rapport propose un \u00ab article 5 bis \u00bb contre la guerre ...",
                "fullMatchingImages": [
                    {
                        "url": "https://m.epochtimes.fr/assets/uploads/2018/05/5890bc863e4b76cd9e46f92e30c70302.jpg"
                    }
                ]
            },
            {
                "url": "http://djamazz.centerblog.net/181.html",
                "pageTitle": "181 - Djamazz .... El Jaza&#39;ir ... i3lam - Centerblog",
                "fullMatchingImages": [
                    {
                        "url": "https://www.alterinfo.net/photo/art/default/22535137-25193413.jpg?v=1527444712"
                    }
                ]
            },
            {
                "url": "https://regnum.ru/pictures/2259079/21.html",
                "pageTitle": "\u0424\u043b\u0430\u0433\u0438 \u0441\u0442\u0440\u0430\u043d-\u0443\u0447\u0430\u0441\u0442\u043d\u0438\u0446 \u0443 \u0448\u0442\u0430\u0431-\u043a\u0432\u0430\u0440\u0442\u0438\u0440\u044b \u041d\u0410\u0422\u041e. (cc ... - \u0418\u0410 Regnum",
                "fullMatchingImages": [
                    {
                        "url": "https://regnum.ru/uploads/pictures/news/2017/04/05/regnum_picture_1491391006145636_normal.jpg"
                    }
                ]
            },
            {
                "url": "http://djamazz.centerblog.net/6593509-otan-un-article-5-bis-contre-la-guerre-hybride",
                "pageTitle": "Otan: ... un \u00ab article 5 bis \u00bb contre la guerre \u00ab hybride \u00bb",
                "fullMatchingImages": [
                    {
                        "url": "https://www.alterinfo.net/photo/art/default/22535137-25193413.jpg?v=1527444712"
                    }
                ]
            },
            {
                "url": "http://djamazz.centerblog.net/194.html",
                "pageTitle": "194 - Djamazz .... El Jaza&#39;ir ... i3lam - Centerblog",
                "fullMatchingImages": [
                    {
                        "url": "https://www.alterinfo.net/photo/art/default/22535137-25193413.jpg?v=1527444712"
                    }
                ]
            },
            {
                "url": "http://djamazz.centerblog.net/rub-Defense-militaire-Securite-17.html",
                "pageTitle": "Defense militaire Securite - Page 17 - Djamazz .... El Jaza&#39;ir ... i3lam",
                "fullMatchingImages": [
                    {
                        "url": "https://www.alterinfo.net/photo/art/default/22535137-25193413.jpg?v=1527444712"
                    }
                ]
            },
            {
                "url": "http://mynextcar.info/pics/complex-van-het-rijksvastgoedbedrijf",
                "pageTitle": "Complex Van Het Rijksvastgoedbedrijf - Mynextcar",
                "fullMatchingImages": [
                    {
                        "url": "https://upload.wikimedia.org/wikipedia/commons/thumb/d/d4/NATO_complex_The_Hague%2C_Waalsdorperweg.jpg/640px-NATO_complex_The_Hague%2C_Waalsdorperweg.jpg"
                    }
                ]
            }
        ],
        "visuallySimilarImages": [
            {
                "url": "https://networkcultures.org/longform/wp-content/uploads/sites/31/2015/05/henner2.jpg"
            }
        ],
        "bestGuessLabels": [
            {
                "label": "nato den haag",
                "languageCode": "nl"
            }
        ]
    }
}