{
    "labelAnnotations": [
        {
            "mid": "/m/01g5v",
            "description": "blue",
            "score": 0.96839064,
            "topicality": 0.96839064
        },
        {
            "mid": "/m/03120",
            "description": "flag",
            "score": 0.9033527,
            "topicality": 0.9033527
        },
        {
            "mid": "/m/01bqvp",
            "description": "sky",
            "score": 0.8412661,
            "topicality": 0.8412661
        },
        {
            "mid": "/m/03jn2m",
            "description": "azure",
            "score": 0.82478213,
            "topicality": 0.82478213
        },
        {
            "mid": "/m/02n3pb",
            "description": "product",
            "score": 0.62550396,
            "topicality": 0.62550396
        },
        {
            "mid": "/m/02vwbzz",
            "description": "electric blue",
            "score": 0.58417183,
            "topicality": 0.58417183
        }
    ],
    "safeSearchAnnotation": {
        "adult": "VERY_UNLIKELY",
        "spoof": "VERY_UNLIKELY",
        "medical": "VERY_UNLIKELY",
        "violence": "VERY_UNLIKELY",
        "racy": "VERY_UNLIKELY"
    },
    "imagePropertiesAnnotation": {
        "dominantColors": {
            "colors": [
                {
                    "color": {
                        "red": 32,
                        "green": 66,
                        "blue": 183
                    },
                    "score": 0.1475937,
                    "pixelFraction": 0.059754223
                },
                {
                    "color": {
                        "red": 60,
                        "green": 121,
                        "blue": 221
                    },
                    "score": 0.14613079,
                    "pixelFraction": 0.09016897
                },
                {
                    "color": {
                        "red": 179,
                        "green": 199,
                        "blue": 231
                    },
                    "score": 0.005104129,
                    "pixelFraction": 0.0060675885
                },
                {
                    "color": {
                        "red": 233,
                        "green": 233,
                        "blue": 239
                    },
                    "score": 0.0025769407,
                    "pixelFraction": 0.013978494
                },
                {
                    "color": {
                        "red": 53,
                        "green": 117,
                        "blue": 229
                    },
                    "score": 0.13093734,
                    "pixelFraction": 0.061981566
                },
                {
                    "color": {
                        "red": 64,
                        "green": 143,
                        "blue": 252
                    },
                    "score": 0.1107982,
                    "pixelFraction": 0.050768048
                },
                {
                    "color": {
                        "red": 74,
                        "green": 145,
                        "blue": 248
                    },
                    "score": 0.10654844,
                    "pixelFraction": 0.05499232
                },
                {
                    "color": {
                        "red": 69,
                        "green": 152,
                        "blue": 247
                    },
                    "score": 0.082240514,
                    "pixelFraction": 0.04623656
                },
                {
                    "color": {
                        "red": 23,
                        "green": 46,
                        "blue": 161
                    },
                    "score": 0.06820842,
                    "pixelFraction": 0.021198157
                },
                {
                    "color": {
                        "red": 233,
                        "green": 251,
                        "blue": 219
                    },
                    "score": 0.00049558276,
                    "pixelFraction": 0.00023041475
                }
            ]
        }
    },
    "cropHintsAnnotation": {
        "cropHints": [
            {
                "boundingPoly": {
                    "vertices": [
                        [],
                        {
                            "x": 699
                        },
                        {
                            "x": 699,
                            "y": 465
                        },
                        {
                            "y": 465
                        }
                    ]
                },
                "confidence": 0.79999995,
                "importanceFraction": 1
            }
        ]
    },
    "webDetection": {
        "webEntities": [
            {
                "entityId": "/m/011pz8s_",
                "score": 1.0401601,
                "description": "2014 Wales summit"
            },
            {
                "entityId": "/t/27cdxz_3bh16y",
                "score": 0.7364
            },
            {
                "entityId": "/m/059dn",
                "score": 0.7364,
                "description": "NATO"
            },
            {
                "entityId": "/m/03cfqp",
                "score": 0.709,
                "description": "Flag of NATO"
            },
            {
                "entityId": "/m/09c7w0",
                "score": 0.6831,
                "description": "United States of America"
            },
            {
                "entityId": "/m/0_6t_z8",
                "score": 0.6588,
                "description": "European Union"
            },
            {
                "entityId": "/m/011brg_r",
                "score": 0.5468,
                "description": "Member states of NATO"
            },
            {
                "entityId": "/m/01h6rj",
                "score": 0.5461,
                "description": "Military"
            },
            {
                "entityId": "/m/05qbbhd",
                "score": 0.5437,
                "description": "Secretary General of NATO"
            },
            {
                "entityId": "/m/0416p41",
                "score": 0.5125,
                "description": "Enlargement of NATO"
            },
            {
                "entityId": "/t/2559cfx2jwyf6",
                "score": 0.4983
            },
            {
                "entityId": "/m/06_ts9c",
                "score": 0.4944,
                "description": "NATO Association of Canada"
            },
            {
                "entityId": "/t/26tx7xy9_tgvr",
                "score": 0.4774
            },
            {
                "entityId": "/m/02r330x",
                "score": 0.19227001,
                "description": "NATO summit"
            },
            {
                "entityId": "/m/011h_gch",
                "score": 0.087885,
                "description": "Oana Lungescu"
            }
        ],
        "fullMatchingImages": [
            {
                "url": "https://www.thesun.co.uk/wp-content/uploads/2016/11/nintchdbpict000282644453.jpg?w={width}"
            },
            {
                "url": "https://content.epodreczniki.pl/content/womi/120716/classic-1920.png"
            },
            {
                "url": "http://3.bp.blogspot.com/-VkClbwsjLiU/UzvF9nRaNqI/AAAAAAAAwXE/yh6tivsdQEU/s1600/NATO-flag-in-the-wind.jpg"
            },
            {
                "url": "https://www.cotidianul.ro/wp-content/uploads/2018/01/26/nato.qr5n7agw4u.jpg"
            },
            {
                "url": "http://h4.telegchannel.com/2018/04/11/082/5940320644229082202_y.jpeg"
            },
            {
                "url": "https://www.thesun.co.uk/wp-content/uploads/2016/11/nintchdbpict000282644453.jpg?strip=all&quality=100&w=1200&h=800&crop=1"
            },
            {
                "url": "https://ipolitics.ca/wp-content/uploads/2015/02/Screen-Shot-2015-02-27-at-3.02.15-PM.png"
            },
            {
                "url": "http://%D1%83%D0%BA%D1%80%D0%BE%D0%BF.org/wp-content/uploads/2015/11/1446510838_nato.jpg"
            },
            {
                "url": "https://www.cotidianul.ro/wp-content/uploads/2018/01/26/nato.qr5n7agw4u-1000x600.jpg"
            },
            {
                "url": "https://static.lsm.lv/media/2014/04/large/0/2ni2.jpg"
            },
            {
                "url": "http://lastpoint.gr/wp-content/uploads/2018/04/simaia-simai.jpg"
            },
            {
                "url": "https://media.novinky.cz/870/508706-original1-vi3pa.jpg"
            },
            {
                "url": "https://pbs.twimg.com/media/DedPHhvW4AMs3z-.jpg"
            },
            {
                "url": "http://oeirasdigital.pt/uploads/201703291339x1C6E.jpg"
            },
            {
                "url": "http://dialogplus.ch/wp-content/uploads/2015/08/20100416_100415a-HQ28-007_rdax_775x5161.jpg"
            },
            {
                "url": "https://iasbh.tmgrup.com.tr/37db2d/0/0/0/0/0/0?u=http://i.sabah.com.tr/sb/galeri/turkiye/10-soruda-ucak-krizi/6.jpg&mw=752&mh=700"
            },
            {
                "url": "http://infobiatorbagy.hu/external/image_cache/a/c/5/ac54954f567519a68bd9176694304f2a.jpg"
            },
            {
                "url": "https://www.haber.ba/wp-content/uploads/2015/10/Nato.jpg?x89719"
            },
            {
                "url": "https://media.realitatea.net/multimedia/image/201705/w728/natooo_59970900.jpg"
            },
            {
                "url": "https://img.diytrade.com/smimg/1954081/44467068-6144889-20_0_0_0_0/nn/3518.jpg"
            },
            {
                "url": "https://www.protinews.gr/sites/default/files/styles/resize_750x450/public/natoflag.jpg?itok=eeN4qDU8"
            },
            {
                "url": "http://www.fnews.gr/wp-content/uploads/2018/07/natoflag.jpg"
            },
            {
                "url": "http://protevousa.com/wp-content/uploads/2017/10/natoflag.jpg"
            },
            {
                "url": "https://www.romania-insider.com/wp-content/uploads/2013/04/nato-flag.jpg"
            },
            {
                "url": "http://2.bp.blogspot.com/-GSThMLPfP8U/VmLSg45AauI/AAAAAAAACbk/_1v936VZRmw/s1600/nato%2B4.jpg"
            },
            {
                "url": "https://cdn1.img.sputnik-news.ee/images/301/53/3015369.jpg"
            },
            {
                "url": "https://knowterrorists.com/wp-content/uploads/2016/07/20100416_100415a-HQ28-007_rdax_775x516.jpg"
            },
            {
                "url": "https://www.extremnews.com/images/max_image_view-787df8571bff423da3e417345efb05d8.jpg"
            },
            {
                "url": "https://image.zn.ua/media/images/645x426/Apr2015/113489.jpg"
            },
            {
                "url": "http://46bah7dkfu-flywheel.netdna-ssl.com/wp-content/uploads/2016/08/nato-3.jpg"
            },
            {
                "url": "https://fakty.ua/photos/article/23/88/238810.jpg"
            },
            {
                "url": "https://www.rbc.ua/static/img/n/a/nato_int8_id8276_650x410_3_650x410_1_650x410.jpg"
            },
            {
                "url": "https://gs-img.112.ua/original/2017/08/23/310845.jpg"
            },
            {
                "url": "https://www.rbc.ua/static/img/_/f/_flag_nato_int_1_650x410.jpg"
            },
            {
                "url": "https://cdn.sindonews.net/dyn/620/content/2015/11/25/40/1064508/dubes-rusia-nato-organisasi-berbahaya-doC.jpg"
            },
            {
                "url": "http://images.unian.net/photos/2014_02/1392028761-8610-nato-foto-natoint.jpg"
            },
            {
                "url": "https://media.realitatea.net/multimedia/image/201705/full/natooo_59970900.jpg"
            },
            {
                "url": "https://4nieuws.nl/media/items/navo.jpg"
            },
            {
                "url": "https://www.army-technology.com/wp-content/uploads/sites/3/2017/09/NATOflagL.jpg"
            },
            {
                "url": "https://cdn1.defesaaereanaval.com.br/wp-content/uploads/2014/02/NATO-flag-in-the-wind-600x399.jpg"
            },
            {
                "url": "https://www.investicniweb.cz/Files/44182-nato/?width=600"
            },
            {
                "url": "https://static.wixstatic.com/media/4e37bc_da8c604ef9384ccd8290ad2056ae7856~mv2.jpg/v1/fill/w_598,h_398,al_c,q_80,usm_0.66_1.00_0.01/4e37bc_da8c604ef9384ccd8290ad2056ae7856~mv2.webp"
            },
            {
                "url": "https://nv.ua/img/article/24733/56_main.jpeg"
            },
            {
                "url": "https://www.channelstv.com/wp-content/uploads/2015/10/nato.jpg"
            },
            {
                "url": "https://docplayer.net/docs-images/79/79586278/images/80-1.jpg"
            },
            {
                "url": "https://images-blogger-opensocial.googleusercontent.com/gadgets/proxy?url=http://3.bp.blogspot.com/-VkClbwsjLiU/UzvF9nRaNqI/AAAAAAAAwXI/oLBw3lIp4So/s560/NATO-flag-in-the-wind.jpg&container=blogger&gadget=a&rewriteMime=image/*"
            },
            {
                "url": "http://3.bp.blogspot.com/-VkClbwsjLiU/UzvF9nRaNqI/AAAAAAAAwXI/oLBw3lIp4So/s560/NATO-flag-in-the-wind.jpg"
            },
            {
                "url": "http://svobodnenoviny.eu/wp-content/uploads/nato_flag.jpg"
            },
            {
                "url": "http://seraj24.ir/images/news/172932/thumbs/thumb2_172932.jpg"
            },
            {
                "url": "https://gordonua.com/img/article/2042/52_tn.jpg"
            },
            {
                "url": "http://gordonua.com/img/article/2470/46_main.jpg"
            },
            {
                "url": "http://altun.az/uploads/posts/2018-02/thumbs/1518455364_nato2.jpg"
            },
            {
                "url": "http://www.ypervasinews.gr/news/wp-content/uploads/2015/10/%CE%9D%CE%91%CE%A4%CE%9F-%CE%A3%CE%97%CE%9C%CE%91%CE%99%CE%91.jpg"
            },
            {
                "url": "http://www.news-cloud.net/uploads/posts/2016-01/1453446722_1927920616.jpg"
            },
            {
                "url": "http://4.bp.blogspot.com/-ttTYWBajf-0/Tx5TlEpbQhI/AAAAAAAARaM/osXQKg29V04/s1600/un.jpg"
            },
            {
                "url": "https://www.akta.ba/resources/Article/LargeImages/d3226c07-b06b-4502-b054-08b77dd09842NATO12.jpg"
            },
            {
                "url": "https://www.wikisosyalizm.org/images/thumb/0/0a/Nato23.jpg/400px-Nato23.jpg"
            },
            {
                "url": "http://3.bp.blogspot.com/-VkClbwsjLiU/UzvF9nRaNqI/AAAAAAAAwXI/oLBw3lIp4So/s400/NATO-flag-in-the-wind.jpg&container=blogger&gadget=a&rewriteMime=image"
            },
            {
                "url": "https://panobcan.sk/wp-content/uploads/2016/06/nato_zastava.jpg"
            },
            {
                "url": "http://www.atlanteguerre.it/wp-content/uploads/2017/05/nato-bandiera-376x250.jpg"
            },
            {
                "url": "https://www.extremnews.com/images/article_landscape-787df8571bff423da3e417345efb05d8.jpg"
            },
            {
                "url": "http://lastpoint.gr/wp-content/uploads/2018/04/simaia-simai-390x205.jpg"
            },
            {
                "url": "https://www.cotidianul.ro/wp-content/uploads/2017/10/nato.qr5n7agw4u-326x245.jpg"
            },
            {
                "url": "https://www.cotidianul.ro/wp-content/uploads/2017/11/13/nato.qr5n7agw4u-326x245.jpg"
            },
            {
                "url": "https://www.newsbeast.gr/files/1/2016/10/natoflag-353x221.jpg"
            },
            {
                "url": "https://s.nbst.gr/files/1/2016/10/natoflag-353x221.jpg"
            },
            {
                "url": "https://cdn.mashreghnews.ir/d/2017/05/27/2/1949311.jpg"
            },
            {
                "url": "https://www.belvpo.com/wp-content/uploads/2012/05/3150io89876789.jpg"
            },
            {
                "url": "http://webpublicapress.net/wp-content/uploads/2014/11/NATO-Zastava-300x199.jpg"
            },
            {
                "url": "https://assets.publishing.service.gov.uk/government/uploads/system/uploads/image_data/file/16385/s300_Nato-flag-960.jpg"
            },
            {
                "url": "https://media.realitatea.net/multimedia/image/201705/w298/natooo_59970900.jpg"
            },
            {
                "url": "https://media.isna.ir/content/1411469574551_NATO-flag.jpg/2"
            },
            {
                "url": "http://www.fggam.org/wp-content/uploads/2014/03/NATO.jpg"
            },
            {
                "url": "https://imgclf.112.ua/277x167/2017/08/23/310845.jpg?timestamp=1503479900"
            },
            {
                "url": "https://gordonua.com/img/article/1141/22_tn2.jpg"
            },
            {
                "url": "https://gordonua.com/img/article/2042/52_tn2.jpg"
            },
            {
                "url": "https://gordonua.com/img/article/1078/20_tn2.jpg"
            },
            {
                "url": "https://gordonua.com/img/article/2427/87_tn2.jpg"
            },
            {
                "url": "https://gordonua.com/img/article/1074/37_tn2.jpg"
            },
            {
                "url": "https://www.adnews.ro/inc/2017/04/57494-218x150.jpg"
            },
            {
                "url": "https://mmbiz.qlogo.cn/mmbiz/5puaLG5r4aZAA7qzwCiccQ8NBjWdQUXicRECiaXcKGiaNUHQwc5QP0O9Im1iaoEIlLIJ8WlkpDvCMDdibexhrdibictzQw/0"
            },
            {
                "url": "https://www.patrasevents.gr/imgsrv/f/188x/2631709.jpg"
            },
            {
                "url": "http://img.giaoduc.net.vn/w150/Uploaded/2018/yrfjpysfzyr/2014_12_24/co_na_to.jpg"
            },
            {
                "url": "http://mediamall.am/timthumb.php?src=upload/blogs/57294.png&w=150&h=100&mt=1505689894"
            },
            {
                "url": "http://websavar.ir/files/fa/news/1393/1/23/8394_967.jpg"
            },
            {
                "url": "http://www.flagbannermaker.com/pic/small/550_0.jpg"
            }
        ],
        "partialMatchingImages": [
            {
                "url": "https://bigthink-img.rbl.ms/simage/https%3A%2F%2Fassets.rbl.ms%2F18578865%2F980x.jpg/2000%2C2000/NnBKLcQ5ESKCDJA3/img.jpg"
            },
            {
                "url": "https://www.vankovska.com/wp-content/uploads/2017/05/nato-cropped.jpg"
            },
            {
                "url": "http://img.salamnews.org/087289c72c1459a39cd2b78171468180/nato_flag_new_627.jpg"
            },
            {
                "url": "http://milenkojovanov.com/wp-content/uploads/2014/12/nato-flag-1024x681.jpg"
            },
            {
                "url": "https://lookaside.fbsbx.com/lookaside/crawler/media/?media_id=448207075316134"
            },
            {
                "url": "https://www.vaken.se/wp/wp-content/uploads/2016/02/nato_flagga.png"
            },
            {
                "url": "https://www.vankovska.com/wp-content/uploads/2017/05/nato-cropped-1024x512.jpg"
            },
            {
                "url": "http://2.bp.blogspot.com/-nNTxY0IlR9I/Uzt4iLNZ8pI/AAAAAAAAKyc/4Y9wacRFjCM/s1600/nato.jpg"
            },
            {
                "url": "https://spi3.itvnet.lv/upload2/articles/70/702595/images/Eiropas-diena-2.jpg"
            },
            {
                "url": "https://media.isna.ir/content/1411469574551_NATO-flag.jpg/4"
            },
            {
                "url": "https://www.forces.net/sites/default/files/styles/cover_image/public/natoflag_0.jpg?itok=wyvaUUeR"
            },
            {
                "url": "https://cdn.cnn.com/cnnnext/dam/assets/151125174232-nato-flag-exlarge-169.jpg"
            },
            {
                "url": "https://miro.medium.com/max/854/1*kFM7fkpLM4Qde9RJamcmEw.jpeg"
            },
            {
                "url": "https://t1.daumcdn.net/cfile/tistory/263CC23C5795C88518"
            },
            {
                "url": "https://pbs.twimg.com/media/DExWiAbWsAAmf7g.jpg"
            },
            {
                "url": "https://webnews.bg/uploads/images/58/0258/210258/768x432.jpg?_=1448378891"
            },
            {
                "url": "http://timeua.info/image/4394"
            },
            {
                "url": "http://cdn.playbuzz.com/cdn//a715be99-2628-4d74-a038-c556dd6e92cd/c44a402c-7bbc-4fb1-8985-c574f0b033d5.jpg"
            },
            {
                "url": "https://iasbh.tmgrup.com.tr/78124b/752/395/0/24/400/234?u=https://isbh.tmgrup.com.tr/sbh/2018/10/04/natodan-rusyaya-uyari-caydirici-olacagiz-1538662843775.jpg"
            },
            {
                "url": "https://www.vankovska.com/wp-content/uploads/2017/05/nato-cropped-768x384.jpg"
            },
            {
                "url": "https://www.vankovska.com/wp-content/uploads/2017/05/nato-cropped-678x381.jpg"
            },
            {
                "url": "http://siyasihaber3.org/images/original/2018/02/02/economist-turkiye-ve-nato-birbirinden-kopuyor-ama-dayanismak-zorunda-kalacak-1517553379.jpg"
            },
            {
                "url": "https://euroislam.pl/app/uploads/2016/07/1-24.jpg"
            },
            {
                "url": "http://i.bigpara.com/i/55big/NATO.jpg"
            },
            {
                "url": "https://www.haberx.com/user/gallery/201809171355201-nato-suriye-kiyilarindaki-savas-gemilerini-artiriyor-26939.jpg"
            },
            {
                "url": "https://iasbh.tmgrup.com.tr/cec03d/650/344/0/24/400/234?u=https://isbh.tmgrup.com.tr/sbh/2018/10/04/natodan-rusyaya-uyari-caydirici-olacagiz-1538662843775.jpg"
            },
            {
                "url": "https://images.teleborsa.it/t/accaddeoggi/18846.t.W630.H354.M4.jpg"
            },
            {
                "url": "http://www.ve.lt/uploads/img/catalog/1/1648/597/nato-lietuvoje-dabartine-situacija-ir-lukesciai-.jpg"
            },
            {
                "url": "https://s1.akhbarona.com/thumbs/article_large/b/e/20160319_160319_nato_turkey_960444741.jpg"
            },
            {
                "url": "http://xeberle.com/uploads/posts/2017-11/medium/1511172461_nato-turkey.jpg"
            },
            {
                "url": "https://nv.ua/img/article/24733/56_share_ukr.jpeg"
            },
            {
                "url": "https://www.regjeringen.no/globalassets/imgpreviews/00/00/03/99/39904_img___1396014900.jpg"
            },
            {
                "url": "https://www.krstarica.com/wp-content/uploads/2015/07/nato2_1437632760.350x197_rss-600x315.jpg"
            },
            {
                "url": "https://telegraf.com.ua/files/2018/02/11081-567x309.jpg"
            },
            {
                "url": "https://media.isna.ir/content/1411469574551_NATO-flag.jpg/3"
            },
            {
                "url": "https://gordonua.com/img/article/3294/82_tn.jpg"
            },
            {
                "url": "https://gordonua.com/img/article/2489/15_tn.jpg"
            },
            {
                "url": "http://gordonua.com/img/article/2537/89_tn.jpg"
            },
            {
                "url": "https://www.vankovska.com/wp-content/uploads/2017/05/nato-cropped-500x250.jpg"
            },
            {
                "url": "https://www.vankovska.com/wp-content/uploads/2017/05/nato-cropped-470x246.jpg"
            },
            {
                "url": "https://www.vankovska.com/wp-content/uploads/2017/05/nato-cropped-450x253.jpg"
            },
            {
                "url": "https://www.investicniweb.cz/Files/44182-nato/?width=400&height=225&crop=1"
            },
            {
                "url": "https://media.canal3.md/image/201708/medium/nato1_41133000.jpg"
            },
            {
                "url": "https://www.vankovska.com/wp-content/uploads/2017/05/nato-cropped-400x200.jpg"
            },
            {
                "url": "https://www.protinews.gr/sites/default/files/styles/latest_articles/public/natoflag.jpg?itok=nOFQ3iDW"
            },
            {
                "url": "https://i0.wp.com/news247worldpressuk.com/wp-content/uploads/2015/08/20100416_100415a-hq28-007_rdax_775x516.jpg?fit=775%2C516&ssl=1&resize=350%2C200"
            },
            {
                "url": "https://i1.wp.com/news.usni.org/wp-content/uploads/2014/06/nato.jpg?resize=350%2C200&ssl=1"
            },
            {
                "url": "https://i0.wp.com/news247worldpressuk.com/wp-content/uploads/2015/08/20100416_100415a-hq28-007_rdax_775x516.jpg?resize=350%2C200&ssl=1"
            },
            {
                "url": "https://www.krstarica.com/wp-content/uploads/2015/07/nato2_1437632760.350x197_rss.jpg"
            },
            {
                "url": "https://www.protinews.gr/sites/default/files/styles/blog_list/public/natoflag.jpg?itok=9bB9WBq7"
            },
            {
                "url": "http://odnako.su/upload/images/medium/2015/03/23/883185_1403992833-9290-nato-foto-natoint.jpg"
            },
            {
                "url": "https://novostipmr.com/sites/default/files/styles/4col/public/filefield_paths/_15632_650x410.jpg?itok=FbQ4_W-2"
            },
            {
                "url": "http://ankaenstitusu.com/wp-content/uploads/2017/02/20160319_160319-nato-turkey-e1516037119356-263x164.jpg"
            },
            {
                "url": "https://www.daily-news.gr/wp-content/uploads/2018/10/natoflag-238x178.jpg"
            },
            {
                "url": "https://cdn2.defesaaereanaval.com.br/wp-content/uploads/2014/02/NATO-flag-in-the-wind-280x140.jpg"
            },
            {
                "url": "https://gordonua.com/img/article/2496/37_tn2.jpg"
            },
            {
                "url": "https://gordonua.com/img/article/2489/15_tn2.jpg"
            },
            {
                "url": "https://gordonua.com/img/article/3294/82_tn2.jpg"
            },
            {
                "url": "https://gdb.rferl.org/19943DCA-8F4A-401C-88A2-D4E3451598F5_cx0_cy1_cw0_w256_r1.jpg"
            },
            {
                "url": "https://www.army-technology.com/wp-content/uploads/sites/3/2017/09/main-2094.jpg"
            },
            {
                "url": "https://rielpolitik.files.wordpress.com/2016/07/images-duckduckgo-com126.jpg?w=220&h=126&crop=1"
            },
            {
                "url": "http://vesti.lv/upload/picture/picture/2017_01/363031/flag_nato_opt-media_thumb.jpg?1484291822"
            },
            {
                "url": "http://ostroum.ru/wp-content/uploads/bfi_thumb/112155-300x300-30cmf5fqaggm5y2kirnoqy.jpg"
            },
            {
                "url": "https://www.pravdiko.mk/wp-content/uploads/2015/03/nato-150x150.jpg"
            },
            {
                "url": "http://www.atlanteguerre.it/wp-content/uploads/2017/05/nato-bandiera-150x150.jpg"
            },
            {
                "url": "https://www.caleaeuropeana.ro/wp-content/uploads/2018/02/nato-flag-150x150.jpg"
            },
            {
                "url": "http://www.ve.lt/uploads/img/catalog/1/1648/597/nato-lietuvoje-dabartine-situacija-ir-lukesciai-1.jpg"
            },
            {
                "url": "https://i.ytimg.com/vi/FGSZSeQoO6I/hqdefault.jpg?sqp=-oaymwEWCKgBEF5IWvKriqkDCQgBFQAAiEIYAQ==&rs=AOn4CLAfR2HHI8J3YDmiVZIgrMbE0Oyhiw"
            },
            {
                "url": "http://analitikaua.net/wp-content/uploads/2014/03/NATO-150x100.jpg"
            },
            {
                "url": "https://frontnews.eu/contents/news/5618/images/resize_XI4MoyAPVuJZsN86K0xtBma235FO71dG_150x90.jpg"
            },
            {
                "url": "https://frontnews.eu/contents/news/510/images/resize_tGe5P9od0LvFfUnh2OH4umxrkEBXAV6R_150x90.jpg"
            },
            {
                "url": "https://frontnews.eu/contents/news/1659/images/resize_vytDZ5dm4P8owS9NOp1kEezjRg37WGfV_150x90.jpg"
            },
            {
                "url": "https://www.vankovska.com/wp-content/uploads/2017/05/nato-cropped-100x100.jpg"
            },
            {
                "url": "https://www.veteranstoday.com/wp-content/uploads/2014/09/NATO-flag-in-the-wind-e1411620227743.jpg"
            },
            {
                "url": "https://i2.wp.com/e-thessalia.gr/wp-content/uploads/2015/06/nato.jpg?fit=708%2C320&ssl=1"
            },
            {
                "url": "https://e-thessalia.gr/wp-content/uploads/2015/06/nato.jpg"
            },
            {
                "url": "http://www.yenikonya.com.tr/uploads/2017/06/29/detay1498724035.jpg"
            },
            {
                "url": "http://oeirasinvest.pt/wp-content/uploads/2017/03/nato-324x160.jpg"
            }
        ],
        "pagesWithMatchingImages": [
            {
                "url": "https://www.army-technology.com/features/featurerelevant-or-useless-nato-celebrates-65th-anniversary-4209841/",
                "pageTitle": "Relevant or useless? <b>NATO</b> celebrates 65th anniversary - Army ...",
                "fullMatchingImages": [
                    {
                        "url": "https://www.army-technology.com/wp-content/uploads/sites/3/2017/09/main-2094.jpg"
                    },
                    {
                        "url": "https://www.army-technology.com/wp-content/uploads/sites/3/2017/09/NATOflagL.jpg"
                    }
                ]
            },
            {
                "url": "https://www.cnn.com/videos/politics/2018/07/10/trump-nato-robertson-pkg-vpx.cnn",
                "pageTitle": "Trump blasts <b>NATO</b> allies ahead of summit - CNN Video - CNN.com",
                "partialMatchingImages": [
                    {
                        "url": "https://cdn.cnn.com/cnnnext/dam/assets/151125174232-nato-flag-exlarge-169.jpg"
                    }
                ]
            },
            {
                "url": "https://edition.cnn.com/video/data/3.0/video/politics/2016/04/22/nato-explained-origwx-bw.cnn/index.xml",
                "pageTitle": "Don&#39;t Miss These Videos",
                "partialMatchingImages": [
                    {
                        "url": "https://cdn.cnn.com/cnnnext/dam/assets/151125174232-nato-flag-exlarge-tease.jpg"
                    }
                ]
            },
            {
                "url": "https://www.nato.int/cps/en/natohq/news_118761.htm",
                "pageTitle": "<b>NATO</b> - News: Statement by <b>NATO</b> spokesperson Oana Lungescu ...",
                "fullMatchingImages": [
                    {
                        "url": "http://www.nato.int/nato_static_fl2014/assets/pictures/hq_graphics/20100416_100415a-HQ28-007_rdax_775x516.jpg"
                    }
                ]
            },
            {
                "url": "https://www.nato.int/cps/en/natohq/news_118654.htm?selectedLocale=en",
                "pageTitle": "<b>NATO</b> - News: Comments to the media by the <b>NATO</b> Spokesperson ...",
                "fullMatchingImages": [
                    {
                        "url": "http://www.nato.int/nato_static_fl2014/assets/pictures/hq_graphics/20100416_100415a-HQ28-007_rdax_775x516.jpg"
                    }
                ]
            },
            {
                "url": "https://www.gov.uk/government/news/pm-announces-britain-will-host-2014-nato-summit--2",
                "pageTitle": "PM announces Britain will host 2014 <b>NATO</b> Summit - GOV.UK",
                "fullMatchingImages": [
                    {
                        "url": "https://assets.publishing.service.gov.uk/government/uploads/system/uploads/image_data/file/16385/s300_Nato-flag-960.jpg"
                    }
                ]
            },
            {
                "url": "https://www.nato.int/cps/en/natohq/news_122048.htm",
                "pageTitle": "<b>NATO</b> - News: Statement by <b>NATO</b> Deputy Spokesperson Carmen ...",
                "fullMatchingImages": [
                    {
                        "url": "http://www.nato.int/nato_static_fl2014/assets/pictures/hq_graphics/20100416_100415a-HQ28-007_rdax_775x516.jpg"
                    }
                ]
            },
            {
                "url": "https://www.nato.int/cps/fr/natohq/topics_64610.htm",
                "pageTitle": "<b>NATO</b> - Topic: <b>NATO</b> Information and Documentation Centre (NIDC ...",
                "fullMatchingImages": [
                    {
                        "url": "http://www.nato.int/nato_static_fl2014/assets/pictures/hq_graphics/20100416_100415a-HQ28-007_rdax_775x516.jpg"
                    }
                ]
            },
            {
                "url": "https://www.army-technology.com/features/featurerelevant-or-useless-nato-celebrates-65th-anniversary-4209841/attachment/featurerelevant-or-useless-nato-celebrates-65th-anniversary-4209841-4/",
                "pageTitle": "Relevant or useless? <b>NATO</b> celebrates 65th ... - Army Technology",
                "fullMatchingImages": [
                    {
                        "url": "https://www.army-technology.com/wp-content/uploads/sites/3/2017/09/NATOflagL.jpg"
                    }
                ]
            },
            {
                "url": "http://natoassociation.ca/nato-enlargement-eastwards-not-just-a-matter-of-geopolitics-part-i/",
                "pageTitle": "<b>NATO</b> Enlargement Eastwards: Not Just a Matter of Geopolitics (Part ...",
                "fullMatchingImages": [
                    {
                        "url": "http://natoassociation.ca/wp-content/uploads/2015/11/nato-flag.jpg"
                    }
                ]
            },
            {
                "url": "https://www.cnn.com/2015/12/02/europe/nato-montenegro-membership-invitation/index.html",
                "pageTitle": "<b>NATO</b> extends membership invite to Montenegro - CNN",
                "partialMatchingImages": [
                    {
                        "url": "https://cdn.cnn.com/cnnnext/dam/assets/151125174232-nato-flag-exlarge-169.jpg"
                    }
                ]
            },
            {
                "url": "https://www.forces.net/news/us-service-member-dies-afghanistan-helicopter-crash",
                "pageTitle": "U.S. Service Member Dies In Afghanistan Helicopter Crash",
                "partialMatchingImages": [
                    {
                        "url": "https://www.forces.net/sites/default/files/styles/cover_image/public/natoflag_0.jpg?itok=wyvaUUeR"
                    }
                ]
            },
            {
                "url": "https://www.vankovska.com/wp-content/uploads/2017/05/?SD",
                "pageTitle": "Index of /wp-content/uploads/2017/05/",
                "partialMatchingImages": [
                    {
                        "url": "https://www.vankovska.com/wp-content/uploads/2017/05/nato-cropped-400x200.jpg"
                    },
                    {
                        "url": "https://www.vankovska.com/wp-content/uploads/2017/05/nato-cropped-100x100.jpg"
                    },
                    {
                        "url": "https://www.vankovska.com/wp-content/uploads/2017/05/nato-cropped-450x253.jpg"
                    },
                    {
                        "url": "https://www.vankovska.com/wp-content/uploads/2017/05/nato-cropped-768x384.jpg"
                    },
                    {
                        "url": "https://www.vankovska.com/wp-content/uploads/2017/05/nato-cropped-470x246.jpg"
                    },
                    {
                        "url": "https://www.vankovska.com/wp-content/uploads/2017/05/nato-cropped-678x381.jpg"
                    },
                    {
                        "url": "https://www.vankovska.com/wp-content/uploads/2017/05/nato-cropped-500x250.jpg"
                    },
                    {
                        "url": "https://www.vankovska.com/wp-content/uploads/2017/05/nato-cropped.jpg"
                    },
                    {
                        "url": "https://www.vankovska.com/wp-content/uploads/2017/05/nato-cropped-1024x512.jpg"
                    }
                ]
            },
            {
                "url": "https://www.army-technology.com/features/featurerelevant-or-useless-nato-celebrates-65th-anniversary-4209841/attachment/featurerelevant-or-useless-nato-celebrates-65th-anniversary-4209841-2/",
                "pageTitle": "Relevant or useless? <b>NATO</b> celebrates 65th ... - Army Technology",
                "fullMatchingImages": [
                    {
                        "url": "https://www.army-technology.com/wp-content/uploads/sites/3/2017/09/NATOflagL.jpg"
                    }
                ]
            },
            {
                "url": "https://www.vankovska.com/wp-content/uploads/2017/05/?DD",
                "pageTitle": "Index of /wp-content/uploads/2017/05/",
                "partialMatchingImages": [
                    {
                        "url": "https://www.vankovska.com/wp-content/uploads/2017/05/nato-cropped-400x200.jpg"
                    },
                    {
                        "url": "https://www.vankovska.com/wp-content/uploads/2017/05/nato-cropped-100x100.jpg"
                    },
                    {
                        "url": "https://www.vankovska.com/wp-content/uploads/2017/05/nato-cropped-450x253.jpg"
                    },
                    {
                        "url": "https://www.vankovska.com/wp-content/uploads/2017/05/nato-cropped-768x384.jpg"
                    },
                    {
                        "url": "https://www.vankovska.com/wp-content/uploads/2017/05/nato-cropped-470x246.jpg"
                    },
                    {
                        "url": "https://www.vankovska.com/wp-content/uploads/2017/05/nato-cropped-678x381.jpg"
                    },
                    {
                        "url": "https://www.vankovska.com/wp-content/uploads/2017/05/nato-cropped-500x250.jpg"
                    },
                    {
                        "url": "https://www.vankovska.com/wp-content/uploads/2017/05/nato-cropped.jpg"
                    },
                    {
                        "url": "https://www.vankovska.com/wp-content/uploads/2017/05/nato-cropped-1024x512.jpg"
                    }
                ]
            },
            {
                "url": "https://www.vankovska.com/wp-content/uploads/2017/05/?MD",
                "pageTitle": "Index of /wp-content/uploads/2017/05/",
                "partialMatchingImages": [
                    {
                        "url": "https://www.vankovska.com/wp-content/uploads/2017/05/nato-cropped-400x200.jpg"
                    },
                    {
                        "url": "https://www.vankovska.com/wp-content/uploads/2017/05/nato-cropped-100x100.jpg"
                    },
                    {
                        "url": "https://www.vankovska.com/wp-content/uploads/2017/05/nato-cropped-450x253.jpg"
                    },
                    {
                        "url": "https://www.vankovska.com/wp-content/uploads/2017/05/nato-cropped-768x384.jpg"
                    },
                    {
                        "url": "https://www.vankovska.com/wp-content/uploads/2017/05/nato-cropped-470x246.jpg"
                    },
                    {
                        "url": "https://www.vankovska.com/wp-content/uploads/2017/05/nato-cropped-678x381.jpg"
                    },
                    {
                        "url": "https://www.vankovska.com/wp-content/uploads/2017/05/nato-cropped-500x250.jpg"
                    },
                    {
                        "url": "https://www.vankovska.com/wp-content/uploads/2017/05/nato-cropped.jpg"
                    },
                    {
                        "url": "https://www.vankovska.com/wp-content/uploads/2017/05/nato-cropped-1024x512.jpg"
                    }
                ]
            },
            {
                "url": "https://www.vankovska.com/wp-content/uploads/2017/05/?MA",
                "pageTitle": "Index of /wp-content/uploads/2017/05/",
                "partialMatchingImages": [
                    {
                        "url": "https://www.vankovska.com/wp-content/uploads/2017/05/nato-cropped-400x200.jpg"
                    },
                    {
                        "url": "https://www.vankovska.com/wp-content/uploads/2017/05/nato-cropped-100x100.jpg"
                    },
                    {
                        "url": "https://www.vankovska.com/wp-content/uploads/2017/05/nato-cropped-450x253.jpg"
                    },
                    {
                        "url": "https://www.vankovska.com/wp-content/uploads/2017/05/nato-cropped-768x384.jpg"
                    },
                    {
                        "url": "https://www.vankovska.com/wp-content/uploads/2017/05/nato-cropped-470x246.jpg"
                    },
                    {
                        "url": "https://www.vankovska.com/wp-content/uploads/2017/05/nato-cropped-678x381.jpg"
                    },
                    {
                        "url": "https://www.vankovska.com/wp-content/uploads/2017/05/nato-cropped-500x250.jpg"
                    },
                    {
                        "url": "https://www.vankovska.com/wp-content/uploads/2017/05/nato-cropped.jpg"
                    },
                    {
                        "url": "https://www.vankovska.com/wp-content/uploads/2017/05/nato-cropped-1024x512.jpg"
                    }
                ]
            },
            {
                "url": "https://www.veteranstoday.com/2014/09/25/neo-will-france-and-germany-challenge-nato/",
                "pageTitle": "NEO - Will France and Germany challenge <b>NATO</b>? - Veterans Today ...",
                "partialMatchingImages": [
                    {
                        "url": "https://www.veteranstoday.com/wp-content/uploads/2014/09/NATO-flag-in-the-wind-e1411620227743.jpg"
                    }
                ]
            },
            {
                "url": "https://www.cnn.com/2016/11/09/politics/trump-nato-challenge/index.html",
                "pageTitle": "<b>NATO</b> and Trump: Are they on a collision course? - CNNPolitics",
                "partialMatchingImages": [
                    {
                        "url": "https://cdn.cnn.com/cnnnext/dam/assets/151125174232-nato-flag-exlarge-169.jpg"
                    }
                ]
            },
            {
                "url": "https://news.usni.org/2018/10/29/panel-nato-eu-need-major-changes-operations-infrastructure-deter-russian-aggression",
                "pageTitle": "Panel: <b>NATO</b>, EU Need Major Changes in Operations, Infrastructure ...",
                "partialMatchingImages": [
                    {
                        "url": "https://i1.wp.com/news.usni.org/wp-content/uploads/2014/06/nato.jpg?resize=350%2C200&ssl=1"
                    }
                ]
            },
            {
                "url": "https://news.usni.org/2018/11/06/official-nato-heart-u-k-defense-strategy-post-european-union-exit",
                "pageTitle": "Official: <b>NATO</b> Heart of U.K. Defense Strategy Post European Union ...",
                "partialMatchingImages": [
                    {
                        "url": "https://i1.wp.com/news.usni.org/wp-content/uploads/2014/06/nato.jpg?resize=350%2C200&ssl=1"
                    }
                ]
            },
            {
                "url": "http://webpublicapress.net/inzko-at-the-u-n-bosnia-to-snuggle-new-politics/",
                "pageTitle": "UN: Bosnia and New Politics | WebPublicaPress",
                "fullMatchingImages": [
                    {
                        "url": "http://webpublicapress.net/wp-content/uploads/2014/11/NATO-Zastava-300x199.jpg"
                    }
                ]
            },
            {
                "url": "https://news.usni.org/2016/06/27/atlantic-council-report-sanctions-increased-nato-military-presence-key-deterring-russia",
                "pageTitle": "Report: Sanctions, <b>NATO</b> Military Increase Key to Deterring Russia",
                "partialMatchingImages": [
                    {
                        "url": "https://i1.wp.com/news.usni.org/wp-content/uploads/2014/06/nato.jpg?resize=350%2C200&ssl=1"
                    }
                ]
            },
            {
                "url": "https://www.thesun.co.uk/news/2194667/nato-defence-spending-country-article-50-cost/",
                "pageTitle": "What is <b>Nato</b>, what does it stand for, what is defence spending by ...",
                "fullMatchingImages": [
                    {
                        "url": "https://www.thesun.co.uk/wp-content/uploads/2016/11/nintchdbpict000282644453.jpg?strip=all&quality=100&w=1200&h=800&crop=1"
                    }
                ]
            },
            {
                "url": "https://www.romania-insider.com/romania-nato-defense-spending-pledge-2018/",
                "pageTitle": "Romania, among <b>NATO</b> countries meeting defense spending ...",
                "fullMatchingImages": [
                    {
                        "url": "https://www.romania-insider.com/wp-content/uploads/2013/04/nato-flag.jpg"
                    }
                ]
            },
            {
                "url": "http://natoassociation.ca/tag/georgia/feed/",
                "pageTitle": "Georgia \u2013 NAOC",
                "fullMatchingImages": [
                    {
                        "url": "http://natoassociation.ca/wp-content/uploads/2015/11/nato-flag.jpg"
                    }
                ]
            },
            {
                "url": "https://bigthink.com/dangerous-ideas/26-disband-nato",
                "pageTitle": "#26: Disband <b>NATO</b> - Big Think",
                "partialMatchingImages": [
                    {
                        "url": "https://bigthink-img.rbl.ms/simage/https%3A%2F%2Fassets.rbl.ms%2F18578865%2F980x.jpg/2000%2C2000/NnBKLcQ5ESKCDJA3/img.jpg"
                    }
                ]
            },
            {
                "url": "http://nosint.blogspot.com/2015/01/new-russian-military-doctrine-names.html",
                "pageTitle": "New Russian Military Doctrine Names <b>NATO</b> Key Risk - Naval Open ...",
                "fullMatchingImages": [
                    {
                        "url": "http://3.bp.blogspot.com/-VkClbwsjLiU/UzvF9nRaNqI/AAAAAAAAwXE/yh6tivsdQEU/s1600/NATO-flag-in-the-wind.jpg"
                    }
                ]
            },
            {
                "url": "https://eng.lsm.lv/article/society/defense/latvia-prepares-nato-crisis-response-agreement.a221738/",
                "pageTitle": "Latvia prepares <b>NATO</b> crisis response agreement / Article / LSM.LV",
                "fullMatchingImages": [
                    {
                        "url": "https://static.lsm.lv/media/2014/04/large/0/2ni2.jpg"
                    }
                ]
            },
            {
                "url": "https://eng.lsm.lv/article/politics/politics/nato-accredits-riga-strategic-communications-center.a96821/",
                "pageTitle": "<b>NATO</b> accredits Riga strategic communications center / Article / LSM ...",
                "fullMatchingImages": [
                    {
                        "url": "https://static.lsm.lv/media/2014/04/large/0/2ni2.jpg"
                    }
                ]
            },
            {
                "url": "http://www.lsm.lv/en/article/politics/vilks-hails-modest-first-step-in-upping-defense-budget.a89554/",
                "pageTitle": "Latvia calls for long-term <b>NATO</b> presence in Baltics / LSM.LV",
                "fullMatchingImages": [
                    {
                        "url": "http://static.lsm.lv/media/2014/04/large/0/2ni2.jpg"
                    }
                ]
            },
            {
                "url": "https://www.romania-insider.com/romanian-president-asks-parliament-approve-nato-counter-intelligence-center-bucharest/",
                "pageTitle": "Bucharest to host <b>NATO</b> counter intelligence detachment | Romania ...",
                "fullMatchingImages": [
                    {
                        "url": "https://www.romania-insider.com/wp-content/uploads/2013/04/nato-flag.jpg"
                    }
                ]
            },
            {
                "url": "https://www.romaniajournal.ro/nato-counter-intelligence-unit-in-romania/",
                "pageTitle": "<b>NATO</b> counter-intelligence unit in Romania - The Romania Journal",
                "fullMatchingImages": [
                    {
                        "url": "https://romaniaj-6651.kxcdn.com/wp-content/uploads/2015/08/nato.jpg"
                    }
                ]
            },
            {
                "url": "https://ipolitics.ca/2015/02/27/how-to-make-nato-matter-again/",
                "pageTitle": "How to make <b>NATO</b> matter again - iPolitics",
                "fullMatchingImages": [
                    {
                        "url": "https://ipolitics.ca/wp-content/uploads/2015/02/Screen-Shot-2015-02-27-at-3.02.15-PM.png"
                    }
                ]
            },
            {
                "url": "https://www.romania-insider.com/nato-headquarters-inaugurated-bucharest/",
                "pageTitle": "<b>NATO</b> headquarters inaugurated in Bucharest next week | Romania ...",
                "fullMatchingImages": [
                    {
                        "url": "https://www.romania-insider.com/wp-content/uploads/2013/04/nato-flag.jpg"
                    }
                ]
            },
            {
                "url": "https://www.romania-insider.com/nato-romania-to-benefit-from-even-stronger-security/",
                "pageTitle": "<b>NATO</b>: Romania to benefit from even stronger security | Romania ...",
                "fullMatchingImages": [
                    {
                        "url": "https://www.romania-insider.com/wp-content/uploads/2013/04/nato-flag.jpg"
                    }
                ]
            },
            {
                "url": "https://eng.lsm.lv/article/politics/politics/latvia-readies-new-riga-nato-comms-center.a90384/",
                "pageTitle": "Latvia readies new Riga <b>Nato</b> comms center / Article / LSM.LV",
                "fullMatchingImages": [
                    {
                        "url": "https://static.lsm.lv/media/2014/04/large/0/2ni2.jpg"
                    }
                ]
            },
            {
                "url": "https://www.forces.net/news/tri-service/nato-invitation-montenegro-prompts-warning-russia",
                "pageTitle": "<b>NATO</b> Invitation To Montenegro Prompts Warning From Russia",
                "partialMatchingImages": [
                    {
                        "url": "https://www.forces.net/sites/default/files/styles/cover_image/public/natoflag_0.jpg?itok=wyvaUUeR"
                    }
                ]
            },
            {
                "url": "http://www.flagbannermaker.com/custom-event-flag-1.html",
                "pageTitle": "Custom event <b>flag</b> - Teardrop <b>flag</b>",
                "fullMatchingImages": [
                    {
                        "url": "http://www.flagbannermaker.com/pic/small/550_0.jpg"
                    }
                ]
            },
            {
                "url": "https://twitter.com/ruforsyth/status/1001929937698377729",
                "pageTitle": "Ruth E. Forsyth on Twitter: &quot;When <b>NATO&#39;s</b> spokesperson needs to ...",
                "fullMatchingImages": [
                    {
                        "url": "https://pbs.twimg.com/media/DedPHhvW4AMs3z-.jpg"
                    }
                ]
            },
            {
                "url": "https://twitter.com/NATOpress/status/1001857512281387012",
                "pageTitle": "Oana Lungescu on Twitter: &quot;#<b>NATO</b> is committed to working with ...",
                "fullMatchingImages": [
                    {
                        "url": "https://pbs.twimg.com/media/DedPHhvW4AMs3z-.jpg"
                    }
                ]
            },
            {
                "url": "http://www.picsnaper.com/p/What-is-Article-5?-And-why-it-matters-CNNPolitics",
                "pageTitle": "Snap What is Article 5 photos on Pinterest",
                "fullMatchingImages": [
                    {
                        "url": "https://www.thesun.co.uk/wp-content/uploads/2016/11/nintchdbpict000282644453.jpg?strip=all&quality=100&w=1200&h=800&crop=1"
                    }
                ]
            },
            {
                "url": "https://news247worldpressuk.com/2015/09/29/jfc-commanders-dsaceur-discuss-nato-readiness-strategy/",
                "pageTitle": "JFC Commanders, DSACEUR discuss <b>NATO</b> readiness, strategy ...",
                "partialMatchingImages": [
                    {
                        "url": "https://i0.wp.com/news247worldpressuk.com/wp-content/uploads/2015/08/20100416_100415a-hq28-007_rdax_775x516.jpg?fit=775%2C516&ssl=1&resize=350%2C200"
                    }
                ]
            },
            {
                "url": "http://www.playbuzz.com/ratibj10/questions-about-nato-and-partnior-countries",
                "pageTitle": "Questions about <b>NATO</b> and Partner countries | Playbuzz",
                "partialMatchingImages": [
                    {
                        "url": "http://cdn.playbuzz.com/cdn//a715be99-2628-4d74-a038-c556dd6e92cd/c44a402c-7bbc-4fb1-8985-c574f0b033d5.jpg"
                    }
                ]
            },
            {
                "url": "https://news247worldpressuk.com/2018/10/13/dutch-contribution-to-nato-exercise-trident-juncture-2018-25-october-to-7-november-marine-navy-luchtmacht-air-force-landmacht-army-with-50000-participants-the-largest-nato-exercise-si/",
                "pageTitle": "Dutch contribution to <b>NATO</b> exercise &#39;Trident Juncture 2018&#39; (25 ...",
                "partialMatchingImages": [
                    {
                        "url": "https://i0.wp.com/news247worldpressuk.com/wp-content/uploads/2015/08/20100416_100415a-hq28-007_rdax_775x516.jpg?resize=350%2C200&ssl=1"
                    }
                ]
            },
            {
                "url": "https://www.ruaviation.com/news/2015/11/24/3949/",
                "pageTitle": "<b>NATO</b> to Issue Statement on Incident With Russian Military Aircraft in ...",
                "fullMatchingImages": [
                    {
                        "url": "https://www.ruaviation.com/images/ii/4df/6f3/4df6f30d88dc38ead056f25d4184aaae.jpg"
                    }
                ]
            },
            {
                "url": "https://news247worldpressuk.com/2015/08/27/raf-hands-over-nato-air-policing-to-luftwaffe-at-amari-estonia/",
                "pageTitle": "RAF hands over <b>NATO</b> Air Policing to Luftwaffe at \u00c4mari, Estonia ...",
                "partialMatchingImages": [
                    {
                        "url": "https://i0.wp.com/news247worldpressuk.com/wp-content/uploads/2015/08/20100416_100415a-hq28-007_rdax_775x516.jpg?fit=775%2C516&ssl=1&resize=350%2C200"
                    }
                ]
            },
            {
                "url": "https://news247worldpressuk.com/2018/08/30/marco-rubio-no-one-was-a-greater-supporter-of-nato-than-senjohnmccain-i-can-think-of-no-one-better-to-name-the-new-nato-hq-after-than-him-please-go-online-and-sign-the-petition/",
                "pageTitle": "Marco Rubio: No one was a greater supporter of <b>NATO</b> than ...",
                "partialMatchingImages": [
                    {
                        "url": "https://i0.wp.com/news247worldpressuk.com/wp-content/uploads/2015/08/20100416_100415a-hq28-007_rdax_775x516.jpg?resize=350%2C200&ssl=1"
                    }
                ]
            },
            {
                "url": "https://theworldnews.net/gb-news/what-is-nato-what-does-it-stand-for-how-much-does-each-country-spend-on-defence-and-what-is-article-5",
                "pageTitle": "What is <b>Nato</b>, what does it stand for, how much does each country ...",
                "fullMatchingImages": [
                    {
                        "url": "https://www.thesun.co.uk/wp-content/uploads/2016/11/nintchdbpict000282644453.jpg?strip=all&quality=100&w=1200&h=800&crop=1"
                    },
                    {
                        "url": "https://www.thesun.co.uk/wp-content/uploads/2016/11/nintchdbpict000282644453.jpg?w={width}"
                    }
                ]
            },
            {
                "url": "https://news.usni.org/2014/06/12/dod-bolstering-cyber-warfare-capabilities-risk-nations",
                "pageTitle": "DoD Bolstering Cyber Warfare Capabilities in at Risk Nations - USNI ...",
                "partialMatchingImages": [
                    {
                        "url": "https://i1.wp.com/news.usni.org/wp-content/uploads/2014/06/nato.jpg?resize=350%2C200&ssl=1"
                    }
                ]
            },
            {
                "url": "http://hotlifestylenews.com/world-news/furious-donald-trump-planning-shake-nato-spending-demands-set-dominate-brussels-summit/",
                "pageTitle": "How a furious Donald Trump is planning to shake up <b>Nato</b> with his ...",
                "fullMatchingImages": [
                    {
                        "url": "https://www.thesun.co.uk/wp-content/uploads/2016/11/nintchdbpict000282644453.jpg?w={width}"
                    }
                ]
            },
            {
                "url": "https://www.army-technology.com/features/market-data/page/11/",
                "pageTitle": "Market Data - Analysis - Army Technology",
                "partialMatchingImages": [
                    {
                        "url": "https://www.army-technology.com/wp-content/uploads/sites/3/2017/09/main-2094.jpg"
                    }
                ]
            },
            {
                "url": "https://defence.pk/pdf/threads/nato-spokesperson-on-nato-russia-founding-act-nato-missile-defence-systems.369297/",
                "pageTitle": "<b>NATO</b> Spokesperson on <b>NATO</b>-Russia founding act, <b>NATO</b> Missile ...",
                "fullMatchingImages": [
                    {
                        "url": "https://defence.pk/pdf/proxy.php?image=http%3A%2F%2Fwww.nato.int%2Fnato_static_fl2014%2Fassets%2Fpictures%2Fhq_graphics%2F20100416_100415a-HQ28-007_rdax_775x516.jpg&hash=b97b259c457a0b75d9482ac2d4d0c586"
                    }
                ]
            },
            {
                "url": "http://world.24-my.info/qatar-is-going-to-join-nato/",
                "pageTitle": "Qatar is going to join <b>NATO</b> | 24-my.info",
                "partialMatchingImages": [
                    {
                        "url": "http://world.24-my.info/wp-content/uploads/2018/06/a73d79b9bd4c5d879e270e0252067f93.jpg"
                    }
                ]
            },
            {
                "url": "http://www.featherflagbanner.com/sdp/1954081/4/cp-7335882/0/Custom_silk_screen_flag.html",
                "pageTitle": "Custom silk screen <b>flag</b> - Custom feather <b>banner</b>, teardrop <b>banner</b> ...",
                "fullMatchingImages": [
                    {
                        "url": "https://img.diytrade.com/smimg/1954081/44467068-6144889-20_0_0_0_0/nn/3518.jpg"
                    }
                ]
            },
            {
                "url": "https://theworldnews.net/gb-news/how-a-furious-donald-trump-is-planning-to-shake-up-nato-with-his-spending-demands-set-to-dominate-brussels-summit",
                "pageTitle": "How a furious Donald Trump is planning to shake up <b>Nato</b> with his ...",
                "fullMatchingImages": [
                    {
                        "url": "https://www.thesun.co.uk/wp-content/uploads/2016/11/nintchdbpict000282644453.jpg?w={width}"
                    }
                ]
            },
            {
                "url": "http://m.featherflagbanner.com/sdm/1954081/4/cp-7335882/0/Custom_silk_screen_flag.html",
                "pageTitle": "Custom silk screen <b>flag</b> - Custom feather <b>banner</b>, teardrop <b>banner</b> ...",
                "fullMatchingImages": [
                    {
                        "url": "https://img.diytrade.com/smimg/1954081/44467068-6144889-20_0_0_0_0/nn/3518.jpg"
                    }
                ]
            },
            {
                "url": "http://opitslinkfest.blogspot.com/2015/07/16-july-blogs-im-following-am.html",
                "pageTitle": "Opit&#39;s LinkFest!: 16 July - Blogs I&#39;m Following am",
                "fullMatchingImages": [
                    {
                        "url": "http://3.bp.blogspot.com/-VkClbwsjLiU/UzvF9nRaNqI/AAAAAAAAwXI/oLBw3lIp4So/s400/NATO-flag-in-the-wind.jpg&container=blogger&gadget=a&rewriteMime=image"
                    }
                ]
            },
            {
                "url": "https://twitter.com/hashtag/natopartners",
                "pageTitle": "#natopartners hashtag on Twitter",
                "fullMatchingImages": [
                    {
                        "url": "https://pbs.twimg.com/media/DedPHhvW4AMs3z-.jpg"
                    }
                ]
            },
            {
                "url": "https://www.channelstv.com/tag/jens-stoltenberg/",
                "pageTitle": "Jens Stoltenberg pagesepsitename%% - Channels TV",
                "fullMatchingImages": [
                    {
                        "url": "https://www.channelstv.com/wp-content/uploads/2015/10/nato.jpg"
                    }
                ]
            },
            {
                "url": "https://knowterrorists.com/nato-ignores-terror-threat-coming-from-south-demonizes-russia-instead-moscow/",
                "pageTitle": "<b>NATO</b> ignores terror threat coming from south, demonizes Russia ...",
                "fullMatchingImages": [
                    {
                        "url": "https://knowterrorists.com/wp-content/uploads/2016/07/20100416_100415a-HQ28-007_rdax_775x516.jpg"
                    }
                ]
            },
            {
                "url": "http://opitslinkfest.blogspot.com/2014/08/2-july-blogs-im-following.html",
                "pageTitle": "Opit&#39;s LinkFest!: 2 August - Blogs I&#39;m Following",
                "fullMatchingImages": [
                    {
                        "url": "https://images-blogger-opensocial.googleusercontent.com/gadgets/proxy?url=http://3.bp.blogspot.com/-VkClbwsjLiU/UzvF9nRaNqI/AAAAAAAAwXI/oLBw3lIp4So/s560/NATO-flag-in-the-wind.jpg&container=blogger&gadget=a&rewriteMime=image/*"
                    }
                ]
            },
            {
                "url": "https://ipolitics.ca/author/julian-lindley-french/",
                "pageTitle": "Julian Lindley-French, Author at iPolitics",
                "fullMatchingImages": [
                    {
                        "url": "https://ipolitics.ca/wp-content/uploads/2015/02/Screen-Shot-2015-02-27-at-3.02.15-PM.png"
                    }
                ]
            },
            {
                "url": "http://opitslinkfest.blogspot.com/2015/01/13-jan-blogs-im-following.html",
                "pageTitle": "Opit&#39;s LinkFest!: 13 Jan - Blogs I&#39;m Following",
                "fullMatchingImages": [
                    {
                        "url": "https://images-blogger-opensocial.googleusercontent.com/gadgets/proxy?url=http://3.bp.blogspot.com/-VkClbwsjLiU/UzvF9nRaNqI/AAAAAAAAwXE/yh6tivsdQEU/s560/NATO-flag-in-the-wind.jpg&container=blogger&gadget=a&rewriteMime=image/*"
                    }
                ]
            },
            {
                "url": "https://docplayer.net/79586278-Issue-37-october-legal-gazette-articles-on-nato-current-challenges.html",
                "pageTitle": "Issue 37. October Legal Gazette. Articles on <b>NATO</b> Current ...",
                "fullMatchingImages": [
                    {
                        "url": "https://docplayer.net/docs-images/79/79586278/images/80-1.jpg"
                    }
                ]
            },
            {
                "url": "https://kirkyil.com/tags/NATOPartners",
                "pageTitle": "NATOPartners photos and hastag",
                "fullMatchingImages": [
                    {
                        "url": "https://pbs.twimg.com/media/DedPHhvW4AMs3z-.jpg"
                    }
                ]
            },
            {
                "url": "http://anayemeni.net/show2721533.html",
                "pageTitle": "What is <b>Nato</b>, what does it stand for, how much does each country ...",
                "fullMatchingImages": [
                    {
                        "url": "https://www.thesun.co.uk/wp-content/uploads/2016/11/nintchdbpict000282644453.jpg?strip=all&quality=100&w=1200&h=800&crop=1"
                    }
                ]
            },
            {
                "url": "https://ipolitics.ca/category/featured-opinion/page/141/",
                "pageTitle": "iDeas Archives - Page 141 of 358 - iPolitics",
                "fullMatchingImages": [
                    {
                        "url": "https://ipolitics.ca/wp-content/uploads/2015/02/Screen-Shot-2015-02-27-at-3.02.15-PM.png"
                    }
                ]
            },
            {
                "url": "https://medium.com/@CrispinBurke/has-recommended",
                "pageTitle": "Stories Crispin J. Burke clapped for \u2013 Medium",
                "partialMatchingImages": [
                    {
                        "url": "https://miro.medium.com/max/854/1*kFM7fkpLM4Qde9RJamcmEw.jpeg"
                    }
                ]
            },
            {
                "url": "https://www.gov.uk/government/news/pm-announces-britain-will-host-2014-nato-summit--2.ur",
                "pageTitle": "\u0646\u06cc\u0679\u0648 2014\u0621\u0633\u0631\u0628\u0631\u0627\u06c1\u06cc \u0627\u062c\u0644\u0627\u0633 \u0628\u0631\u0637\u0627\u0646\u06cc\u06c1 \u0645\u06cc\u06ba \u06c1\u0648\u06af\u0627: \u0648\u0632\u06cc\u0631\u0627\u0639\u0638\u0645 \u0688\u06cc\u0648\u0688 \u06a9\u06cc\u0645\u0631\u0648\u0646 ...",
                "fullMatchingImages": [
                    {
                        "url": "https://assets.publishing.service.gov.uk/government/uploads/system/uploads/image_data/file/16385/s300_Nato-flag-960.jpg"
                    }
                ]
            },
            {
                "url": "http://oeirasinvest.pt/construcao-da-escola-de-comunicacoes-da-nato-em-oeiras-arranca-em-abril/",
                "pageTitle": "Constru\u00e7\u00e3o da escola de comunica\u00e7\u00f5es da <b>NATO</b> em Oeiras ...",
                "fullMatchingImages": [
                    {
                        "url": "http://oeirasinvest.pt/wp-content/uploads/2017/03/nato.jpg"
                    }
                ]
            },
            {
                "url": "http://lastpoint.gr/ti-einai-to-nato/",
                "pageTitle": "\u03a4\u03b9 \u03b5\u03af\u03bd\u03b1\u03b9 \u03c4\u03bf \u039d\u0391\u03a4\u039f; - lastpoint.gr",
                "fullMatchingImages": [
                    {
                        "url": "http://lastpoint.gr/wp-content/uploads/2018/04/simaia-simai.jpg"
                    }
                ]
            },
            {
                "url": "http://dialogplus.ch/100415a-hq28-007-nato-headquarters-brussels-2",
                "pageTitle": "100415a-HQ28-007 <b>NATO</b> Headquarters Brussels. - dialogplus",
                "fullMatchingImages": [
                    {
                        "url": "http://dialogplus.ch/wp-content/uploads/2015/08/20100416_100415a-HQ28-007_rdax_775x5161.jpg"
                    }
                ]
            },
            {
                "url": "http://wijwillenhetweten.nl/2015/08/12/navo-bereidt-zich-voor-op-mogelijke-confrontatie-met-rusland/",
                "pageTitle": "Navo bereidt zich voor op mogelijke confrontatie met Rusland",
                "fullMatchingImages": [
                    {
                        "url": "http://wijwillenhetweten.nl/wp-content/uploads/2015/08/navo.jpg"
                    }
                ]
            },
            {
                "url": "http://www.ve.lt/naujienos/lietuva/lietuva/susitiks-nato-virsunes-lietuvai-atstovaus-prezidente-1647985/",
                "pageTitle": "Susitiks <b>NATO</b> vir\u0161\u016bn\u0117s, Lietuvai atstovaus prezident\u0117",
                "partialMatchingImages": [
                    {
                        "url": "http://www.ve.lt/uploads/img/catalog/1/1647/985/susitiks-nato-virsunes-lietuvai-atstovaus-prezidente.jpg"
                    },
                    {
                        "url": "http://www.ve.lt/uploads/img/catalog/1/1647/985/susitiks-nato-virsunes-lietuvai-atstovaus-prezidente1.jpg"
                    }
                ]
            },
            {
                "url": "https://www.investicniweb.cz/nato-a-vydaje-na-obranu-5-faktu-ktere-je-potreba-znat/",
                "pageTitle": "<b>NATO</b> a v\u00fddaje na obranu: 5 fakt\u016f, kter\u00e9 je pot\u0159eba zn\u00e1t ...",
                "fullMatchingImages": [
                    {
                        "url": "https://www.investicniweb.cz/Files/44182-nato/?width=600"
                    }
                ]
            },
            {
                "url": "http://www.ve.lt/naujienos/lietuva/lietuva/nato-lietuvoje-dabartine-situacija-ir-lukesciai-1648597/",
                "pageTitle": "<b>NATO</b> Lietuvoje: dabartin\u0117 situacija ir l\u016bkes\u010diai - Vakar\u0173 ekspresas",
                "partialMatchingImages": [
                    {
                        "url": "http://www.ve.lt/uploads/img/catalog/1/1648/597/nato-lietuvoje-dabartine-situacija-ir-lukesciai-.jpg"
                    },
                    {
                        "url": "http://www.ve.lt/uploads/img/catalog/1/1648/597/nato-lietuvoje-dabartine-situacija-ir-lukesciai-1.jpg"
                    }
                ]
            },
            {
                "url": "https://euroislam.pl/czas-juz-wykopac-turcje-erdogana-z-nato/",
                "pageTitle": "Czas ju\u017c wykopa\u0107 Turcj\u0119 Erdogana z <b>NATO</b> \u2013 Euroislam \u2013 imigracja ...",
                "partialMatchingImages": [
                    {
                        "url": "https://euroislam.pl/app/uploads/2016/07/1-24.jpg"
                    }
                ]
            },
            {
                "url": "https://www.investicniweb.cz/news-pavel-v-nato-se-meni-duraz-na-vybaveni-a-pripravenost-sil/",
                "pageTitle": "Pavel: V <b>NATO</b> se m\u011bn\u00ed d\u016fraz na vybaven\u00ed a p\u0159ipravenost sil ...",
                "fullMatchingImages": [
                    {
                        "url": "https://www.investicniweb.cz/Files/44182-nato/?width=600"
                    }
                ]
            },
            {
                "url": "http://www.ve.lt/naujienos/klaipeda1/klaipeda/pries-nato-ir-eura-agitave-vyrai-nuteisti-pagristai-1660996/",
                "pageTitle": "Prie\u0161 <b>NATO</b> ir eur\u0105 agitav\u0119 vyrai nuteisti pagr\u012fstai - Vakar\u0173 ekspresas",
                "partialMatchingImages": [
                    {
                        "url": "http://www.ve.lt/uploads/img/catalog/1/1660/996/pries-nato-ir-eura-agitave-vyrai-nuteisti-pagrista.jpg"
                    },
                    {
                        "url": "http://www.ve.lt/uploads/img/catalog/1/1660/996/pries-nato-ir-eura-agitave-vyrai-nuteisti-pagrista1.jpg"
                    }
                ]
            },
            {
                "url": "https://www.regjeringen.no/no/aktuelt/Snart-NATO-toppmote-Hva-mener-Norge-om-fremtiden-for-NATO/id766039/",
                "pageTitle": "Snart <b>NATO</b>-toppm\u00f8te: Hva mener Norge om fremtidens <b>NATO</b> ...",
                "partialMatchingImages": [
                    {
                        "url": "https://www.regjeringen.no/link/34000da9b54c4c1c9f793e8f3652affc.aspx?id=2277395"
                    }
                ]
            },
            {
                "url": "https://www.romaniajournal.ro/nato-office-to-become-operational-in-chisinau-this-autumn/",
                "pageTitle": "<b>NATO</b> office to become operational in Chisinau this autumn - The ...",
                "fullMatchingImages": [
                    {
                        "url": "https://romaniaj-6651.kxcdn.com/wp-content/uploads/2015/08/nato.jpg"
                    }
                ]
            },
            {
                "url": "http://en.eyeni.biz/images/?q=Nato+fahne",
                "pageTitle": "<b>Nato</b> fahne pictures free download - YEN\u0130.MOB\u0130",
                "fullMatchingImages": [
                    {
                        "url": "https://www.thesun.co.uk/wp-content/uploads/2016/11/nintchdbpict000282644453.jpg?strip=all&amp;quality=100&amp;w=1200&amp;h=800&amp;crop=1"
                    }
                ]
            },
            {
                "url": "https://www.regjeringen.no/no/aktuelt/Gratulerer-NATOs-nye-generalsekretar/id754147/",
                "pageTitle": "Gratulerer Stoltenberg som ny generalsekret\u00e6r i <b>NATO</b> - regjeringen ...",
                "partialMatchingImages": [
                    {
                        "url": "https://www.regjeringen.no/globalassets/imgpreviews/00/00/03/99/39904_img___1396014900.jpg"
                    }
                ]
            },
            {
                "url": "http://www.ve.lt/naujienos/lietuva/lietuva/nato-lietuvoje-dabartine-situacija-ir-lukesciai-1648597/susije/",
                "pageTitle": "ve.lt - Vakar\u0173 ekspresas",
                "partialMatchingImages": [
                    {
                        "url": "http://www.ve.lt/uploads/img/catalog/1/1647/985/susitiks-nato-virsunes-lietuvai-atstovaus-prezidente.jpg"
                    }
                ]
            },
            {
                "url": "https://www.caleaeuropeana.ro/romania-in-nato-2004-2016-expozitie-de-fotografie-cu-militarii-romani-in-teatrele-de-operatii-nato-deschisa-la-varsovia/",
                "pageTitle": "Rom\u00e2nia \u00een <b>NATO</b> 2004-2016 \u2013 expozi\u021bie de fotografie cu militarii ...",
                "partialMatchingImages": [
                    {
                        "url": "https://www.caleaeuropeana.ro/wp-content/uploads/2018/02/nato-flag-150x150.jpg"
                    }
                ]
            },
            {
                "url": "http://eyeni.biz/sekil-yukle/?q=Nato+bayragi",
                "pageTitle": "<b>Nato</b> bayragi sor\u011fusuna uy\u011fun \u015fekilleri pulsuz y\u00fckle, bedava indir",
                "fullMatchingImages": [
                    {
                        "url": "https://www.thesun.co.uk/wp-content/uploads/2016/11/nintchdbpict000282644453.jpg?strip=all&amp;quality=100&amp;w=1200&amp;h=800&amp;crop=1"
                    }
                ]
            },
            {
                "url": "http://svobodnenoviny.eu/nato-rika-ze-nyni-ma-duvod-pro-utok-na-rusko/",
                "pageTitle": "<b>NATO</b> \u0159\u00edk\u00e1, \u017ee nyn\u00ed m\u00e1 d\u016fvod pro \u00fatok na Rusko - Svobodn\u00e9 noviny",
                "fullMatchingImages": [
                    {
                        "url": "http://svobodnenoviny.eu/wp-content/uploads/nato_flag.jpg"
                    }
                ]
            },
            {
                "url": "https://www.cotidianul.ro/o-echipa-de-experti-nato-evalueaza-republica-moldova/",
                "pageTitle": "O echip\u0103 de exper\u0163i <b>NATO</b> evalueaz\u0103 Republica Moldova - Cotidianul",
                "fullMatchingImages": [
                    {
                        "url": "https://www.cotidianul.ro/wp-content/uploads/2017/10/nato.qr5n7agw4u-326x245.jpg"
                    }
                ]
            },
            {
                "url": "https://www.novinky.cz/domaci/380242-na-hrade-vitali-sefa-nato-ale-vyvesili-vlajku-osn.html",
                "pageTitle": "Na Hrad\u011b v\u00edtali \u0161\u00e9fa <b>NATO</b>, ale vyv\u011bsili vlajku OSN \u2013 Novinky.cz",
                "fullMatchingImages": [
                    {
                        "url": "https://media.novinky.cz/870/508706-original1-vi3pa.jpg"
                    }
                ]
            },
            {
                "url": "https://www.caleaeuropeana.ro/trei-militari-ai-nato-ucisi-intr-un-atac-sinucigas-in-afganistan-nationalitatea-lor-nu-este-cunoscuta-deocamdata/",
                "pageTitle": "Trei militari ai <b>NATO</b>, uci\u0219i \u00eentr-un atac sinuciga\u0219 \u00een Afganistan ...",
                "fullMatchingImages": [
                    {
                        "url": "https://www.caleaeuropeana.ro/wp-content/uploads/2018/02/nato-flag.jpg"
                    }
                ]
            },
            {
                "url": "https://www.caleaeuropeana.ro/aliatii-au-decis-nato-va-avea-o-noua-structura-de-comanda-pentru-a-face-fata-amenintarilor-romania-s-a-oferit-sa-gazduiasca-un-comandament-la-nivel-de-corp-de-armata/",
                "pageTitle": "Alia\u021bii au decis: <b>NATO</b> va avea o nou\u0103 structur\u0103 de comand\u0103 pentru ...",
                "partialMatchingImages": [
                    {
                        "url": "https://www.caleaeuropeana.ro/wp-content/uploads/2018/02/nato-flag-150x150.jpg"
                    }
                ]
            },
            {
                "url": "https://www.caleaeuropeana.ro/nato-isi-intensifica-prezenta-in-atlantic-a-doua-flota-a-sua-reactivata-dupa-sapte-ani/",
                "pageTitle": "<b>NATO</b> \u00ee\u0219i intensific\u0103 prezen\u021ba \u00een Atlantic. A Doua Flot\u0103 a SUA ...",
                "fullMatchingImages": [
                    {
                        "url": "https://www.caleaeuropeana.ro/wp-content/uploads/2018/02/nato-flag.jpg"
                    }
                ]
            },
            {
                "url": "https://www.cotidianul.ro/romania-este-un-avanpost-amenintator-al-nato/",
                "pageTitle": "Rom\u00e2nia este un avanpost amenin\u0163\u0103tor al <b>NATO</b> - Cotidianul",
                "fullMatchingImages": [
                    {
                        "url": "https://www.cotidianul.ro/wp-content/uploads/2017/10/nato.qr5n7agw4u-1.jpg"
                    }
                ]
            },
            {
                "url": "http://svobodnenoviny.eu/nato-par-poznamek-a-objasneni/",
                "pageTitle": "<b>NATO</b> \u2013 p\u00e1r pozn\u00e1mek a objasn\u011bn\u00ed \u2013 SVOBODN\u00c9 NOVINY BEZ ...",
                "fullMatchingImages": [
                    {
                        "url": "http://svobodnenoviny.eu/wp-content/uploads/nato_flag.jpg"
                    }
                ]
            },
            {
                "url": "http://bigpara.hurriyet.com.tr/haberler/ekonomi-haberleri/nato-zirvesi-bircok-ilke-sahne-olacak_ID1447523/",
                "pageTitle": "<b>NATO</b> Zirvesi bir\u00e7ok ilke sahne olacak | Ekonomi Haberleri",
                "partialMatchingImages": [
                    {
                        "url": "http://i.bigpara.com/i/55big/NATO.jpg"
                    }
                ]
            },
            {
                "url": "http://kathmandutoday.com/2015/10/140382.html",
                "pageTitle": "\u0928\u0947\u091f\u094b\u0932\u0947 \u0930\u0938\u093f\u092f\u093e\u0932\u093e\u0908 \u0926\u093f\u092f\u094b \u092f\u0938\u094d\u0924\u094b \u0906\u0926\u0947\u0936 \u2013 Kathmandutoday ...",
                "fullMatchingImages": [
                    {
                        "url": "http://kathmandutoday.com/wp-content/uploads/2015/10/neto.jpg"
                    }
                ]
            },
            {
                "url": "https://www.cotidianul.ro/presa-rusa-armamentul-greu-al-nato-soseste-in-romania/",
                "pageTitle": "Presa rus\u0103: Armamentul greu al <b>NATO</b> sose\u015fte \u00een Rom\u00e2nia",
                "fullMatchingImages": [
                    {
                        "url": "https://www.cotidianul.ro/wp-content/uploads/2017/11/27/nato.qr5n7agw4u-1000x600.jpg"
                    },
                    {
                        "url": "https://www.cotidianul.ro/wp-content/uploads/2017/11/27/nato.qr5n7agw4u.jpg"
                    }
                ]
            },
            {
                "url": "https://www.cotidianul.ro/nato-raspunde-la-solicitarea-lui-trump/",
                "pageTitle": "<b>NATO</b> r\u0103spunde la solicitarea lui Trump - Cotidianul",
                "fullMatchingImages": [
                    {
                        "url": "https://www.cotidianul.ro/wp-content/uploads/2017/10/c/nato.qr5n7agw4u-1000x600.jpg"
                    },
                    {
                        "url": "https://www.cotidianul.ro/wp-content/uploads/2017/10/c/nato.qr5n7agw4u.jpg"
                    }
                ]
            },
            {
                "url": "https://www.teleborsa.it/Accadde-Oggi/4-maggio/1949-l-italia-sceglie-la-nato-8.html",
                "pageTitle": "Accadde oggi 4 maggio - 1949: L&#39;Italia sceglie la <b>NATO</b> | Teleborsa.it",
                "partialMatchingImages": [
                    {
                        "url": "https://images.teleborsa.it/t/accaddeoggi/18846.t.W630.H354.M4.jpg"
                    }
                ]
            }
        ],
        "visuallySimilarImages": [
            {
                "url": "https://cdn.cnn.com/cnnnext/dam/assets/151125174232-nato-flag-phone-gallery.jpg"
            },
            {
                "url": "https://img.timesnownews.com/story/1531366263-nato_Thinkstock.jpg?d=600x450"
            },
            {
                "url": "https://ak7.picdn.net/shutterstock/videos/14837197/thumb/1.jpg"
            },
            {
                "url": "https://image.shutterstock.com/image-photo/nato-flag-waving-against-clean-260nw-478615099.jpg"
            },
            {
                "url": "http://www.rcinet.ca/eye-on-the-arctic/wp-content/uploads/sites/30/2018/08/nato-flag-belgium-1024x576.jpg"
            },
            {
                "url": "https://bulgarianmilitary.com/wp-content/uploads/2017/10/nato-flag.jpg"
            },
            {
                "url": "http://www.saratogaflag.com/assets/images/VINTAGE%20FLAGS/Nato_Flag_2.jpg"
            },
            {
                "url": "http://news.bbc.co.uk/media/images/40302000/jpg/_40302285_natoflag.jpg"
            }
        ],
        "bestGuessLabels": [
            {
                "label": "nato flag",
                "languageCode": "en"
            }
        ]
    },
    "localizedObjectAnnotations": [
        {
            "mid": "/m/03120",
            "name": "Flag",
            "score": 0.8325369,
            "boundingPoly": {
                "normalizedVertices": [
                    {
                        "x": 0.0624706,
                        "y": 0.090705894
                    },
                    {
                        "x": 0.9281177,
                        "y": 0.090705894
                    },
                    {
                        "x": 0.9281177,
                        "y": 0.89
                    },
                    {
                        "x": 0.0624706,
                        "y": 0.89
                    }
                ]
            }
        }
    ]
}